{
  "audio_files": [
    {
      "relative_source_path": "book-ef193ffc52/book-ef193ffc52.mp3",
      "sha256": "0c0e6f9bad71d8d0a1923118cbbac6bae4c7aefde8c3c33bb25b53ee220775d3",
      "size_bytes": 12723348,
      "source_path": "output/bengali_audiobook_polish/bengali-polish-queue-v1/bundles/ben/book-ef193ffc52/book-ef193ffc52.mp3",
      "storage_status": "LOCAL_SOURCE_ONLY"
    }
  ],
  "candidate_slug": "book-ef193ffc52",
  "copy_internal_requested": false,
  "frontend_build_audio_files": [],
  "frontend_public_audio_files": [],
  "generated_at": "2026-06-23T19:36:08+00:00",
  "internal_copies": [],
  "public_serving_status": "BLOCKED",
  "storage_status": "LOCAL_SOURCE_ONLY",
  "upload_status": "NOT_UPLOADED"
}
