[
  {
    "end_ms": 1248,
    "start_ms": 0,
    "word": "অধ্যায়"
  },
  {
    "end_ms": 1426,
    "start_ms": 1248,
    "word": "1"
  },
  {
    "end_ms": 2317,
    "start_ms": 1426,
    "word": "প্রথম"
  },
  {
    "end_ms": 3744,
    "start_ms": 2317,
    "word": "পরিচ্ছেদ"
  },
  {
    "end_ms": 4496,
    "start_ms": 3744,
    "word": "মুচিরাম"
  },
  {
    "end_ms": 4927,
    "start_ms": 4496,
    "word": "গুড়"
  },
  {
    "end_ms": 5572,
    "start_ms": 4927,
    "word": "মহাশয়"
  },
  {
    "end_ms": 5787,
    "start_ms": 5572,
    "word": "এই"
  },
  {
    "end_ms": 6110,
    "start_ms": 5787,
    "word": "জগৎ"
  },
  {
    "end_ms": 6755,
    "start_ms": 6110,
    "word": "পবিত্র"
  },
  {
    "end_ms": 7400,
    "start_ms": 6755,
    "word": "করিবার"
  },
  {
    "end_ms": 7830,
    "start_ms": 7400,
    "word": "জন্য"
  },
  {
    "end_ms": 8260,
    "start_ms": 7830,
    "word": "কোন্"
  },
  {
    "end_ms": 8583,
    "start_ms": 8260,
    "word": "শকে"
  },
  {
    "end_ms": 9551,
    "start_ms": 8583,
    "word": "জন্মগ্রহণ"
  },
  {
    "end_ms": 10734,
    "start_ms": 9551,
    "word": "করিয়াছিলেন"
  },
  {
    "end_ms": 11487,
    "start_ms": 10734,
    "word": "ইতিহাসে"
  },
  {
    "end_ms": 11917,
    "start_ms": 11487,
    "word": "তাহা"
  },
  {
    "end_ms": 12347,
    "start_ms": 11917,
    "word": "লেখে"
  },
  {
    "end_ms": 12562,
    "start_ms": 12347,
    "word": "না"
  },
  {
    "end_ms": 13208,
    "start_ms": 12562,
    "word": "ইতিহাস"
  },
  {
    "end_ms": 13638,
    "start_ms": 13208,
    "word": "এরূপ"
  },
  {
    "end_ms": 14713,
    "start_ms": 13638,
    "word": "অনেকপ্রকার"
  },
  {
    "end_ms": 15466,
    "start_ms": 14713,
    "word": "বদমাইসি"
  },
  {
    "end_ms": 16111,
    "start_ms": 15466,
    "word": "করিয়া"
  },
  {
    "end_ms": 16541,
    "start_ms": 16111,
    "word": "থাকে"
  },
  {
    "end_ms": 16649,
    "start_ms": 16541,
    "word": "এ"
  },
  {
    "end_ms": 17079,
    "start_ms": 16649,
    "word": "দেশে"
  },
  {
    "end_ms": 17940,
    "start_ms": 17079,
    "word": "ইতিহাসের"
  },
  {
    "end_ms": 18692,
    "start_ms": 17940,
    "word": "সাক্ষাৎ"
  },
  {
    "end_ms": 19338,
    "start_ms": 18692,
    "word": "পাওয়া"
  },
  {
    "end_ms": 19768,
    "start_ms": 19338,
    "word": "যায়"
  },
  {
    "end_ms": 19983,
    "start_ms": 19768,
    "word": "না"
  },
  {
    "end_ms": 20413,
    "start_ms": 19983,
    "word": "নচেৎ"
  },
  {
    "end_ms": 20843,
    "start_ms": 20413,
    "word": "উচিত"
  },
  {
    "end_ms": 21704,
    "start_ms": 20843,
    "word": "ব্যবস্থা"
  },
  {
    "end_ms": 22026,
    "start_ms": 21704,
    "word": "করা"
  },
  {
    "end_ms": 22456,
    "start_ms": 22026,
    "word": "যাইত"
  },
  {
    "end_ms": 22994,
    "start_ms": 22456,
    "word": "যশোদা"
  },
  {
    "end_ms": 23532,
    "start_ms": 22994,
    "word": "দেবীর"
  },
  {
    "end_ms": 24070,
    "start_ms": 23532,
    "word": "গর্ভে"
  },
  {
    "end_ms": 24822,
    "start_ms": 24070,
    "word": "সাফলরাম"
  },
  {
    "end_ms": 25468,
    "start_ms": 24822,
    "word": "গুড়ের"
  },
  {
    "end_ms": 25898,
    "start_ms": 25468,
    "word": "ঔরসে"
  },
  {
    "end_ms": 26543,
    "start_ms": 25898,
    "word": "তাঁহার"
  },
  {
    "end_ms": 26973,
    "start_ms": 26543,
    "word": "জন্ম"
  },
  {
    "end_ms": 27296,
    "start_ms": 26973,
    "word": "ইহা"
  },
  {
    "end_ms": 27941,
    "start_ms": 27296,
    "word": "দুঃখের"
  },
  {
    "end_ms": 28479,
    "start_ms": 27941,
    "word": "বিষয়"
  },
  {
    "end_ms": 29124,
    "start_ms": 28479,
    "word": "সন্দেহ"
  },
  {
    "end_ms": 29447,
    "start_ms": 29124,
    "word": "নাই"
  },
  {
    "end_ms": 29770,
    "start_ms": 29447,
    "word": "কেন"
  },
  {
    "end_ms": 29985,
    "start_ms": 29770,
    "word": "না"
  },
  {
    "end_ms": 30953,
    "start_ms": 29985,
    "word": "উচ্চবংশের"
  },
  {
    "end_ms": 31275,
    "start_ms": 30953,
    "word": "কথা"
  },
  {
    "end_ms": 31813,
    "start_ms": 31275,
    "word": "কিছুই"
  },
  {
    "end_ms": 32351,
    "start_ms": 31813,
    "word": "বলিতে"
  },
  {
    "end_ms": 32781,
    "start_ms": 32351,
    "word": "পারা"
  },
  {
    "end_ms": 33103,
    "start_ms": 32781,
    "word": "গেল"
  },
  {
    "end_ms": 33319,
    "start_ms": 33103,
    "word": "না"
  },
  {
    "end_ms": 33641,
    "start_ms": 33319,
    "word": "তবে"
  },
  {
    "end_ms": 33964,
    "start_ms": 33641,
    "word": "ইহা"
  },
  {
    "end_ms": 34286,
    "start_ms": 33964,
    "word": "বলা"
  },
  {
    "end_ms": 34824,
    "start_ms": 34286,
    "word": "যাইতে"
  },
  {
    "end_ms": 35254,
    "start_ms": 34824,
    "word": "পারে"
  },
  {
    "end_ms": 35470,
    "start_ms": 35254,
    "word": "যে"
  },
  {
    "end_ms": 35900,
    "start_ms": 35470,
    "word": "তিনি"
  },
  {
    "end_ms": 37620,
    "start_ms": 35900,
    "word": "ব্রাহ্মণকুলোদ্ভব"
  },
  {
    "end_ms": 38051,
    "start_ms": 37620,
    "word": "গুড়"
  },
  {
    "end_ms": 38803,
    "start_ms": 38051,
    "word": "শুনিয়া"
  },
  {
    "end_ms": 39126,
    "start_ms": 38803,
    "word": "কেহ"
  },
  {
    "end_ms": 39449,
    "start_ms": 39126,
    "word": "মনে"
  },
  {
    "end_ms": 39664,
    "start_ms": 39449,
    "word": "না"
  },
  {
    "end_ms": 40094,
    "start_ms": 39664,
    "word": "করেন"
  },
  {
    "end_ms": 40309,
    "start_ms": 40094,
    "word": "যে"
  },
  {
    "end_ms": 40739,
    "start_ms": 40309,
    "word": "তিনি"
  },
  {
    "end_ms": 41815,
    "start_ms": 40739,
    "word": "মিষ্টবিশেষ"
  },
  {
    "end_ms": 42245,
    "start_ms": 41815,
    "word": "হইতে"
  },
  {
    "end_ms": 43643,
    "start_ms": 42245,
    "word": "জন্মিয়াছিলেন"
  },
  {
    "end_ms": 44396,
    "start_ms": 43643,
    "word": "সাফলরাম"
  },
  {
    "end_ms": 44826,
    "start_ms": 44396,
    "word": "গুড়"
  },
  {
    "end_ms": 45901,
    "start_ms": 44826,
    "word": "কৈবর্ত্তের"
  },
  {
    "end_ms": 46762,
    "start_ms": 45901,
    "word": "ব্রাহ্মণ"
  },
  {
    "end_ms": 47300,
    "start_ms": 46762,
    "word": "ছিলেন"
  },
  {
    "end_ms": 47945,
    "start_ms": 47300,
    "word": "তাঁহার"
  },
  {
    "end_ms": 48483,
    "start_ms": 47945,
    "word": "নিবাস"
  },
  {
    "end_ms": 49558,
    "start_ms": 48483,
    "word": "সাধুভাষায়"
  },
  {
    "end_ms": 50526,
    "start_ms": 49558,
    "word": "মোহনপল্লী"
  },
  {
    "end_ms": 50849,
    "start_ms": 50526,
    "word": "অপর"
  },
  {
    "end_ms": 51494,
    "start_ms": 50849,
    "word": "ভাষায়"
  },
  {
    "end_ms": 52462,
    "start_ms": 51494,
    "word": "মোনাপাড়া"
  },
  {
    "end_ms": 53430,
    "start_ms": 52462,
    "word": "মোহনপল্লী"
  },
  {
    "end_ms": 53860,
    "start_ms": 53430,
    "word": "ওরফে"
  },
  {
    "end_ms": 55043,
    "start_ms": 53860,
    "word": "মোনাপাড়ায়"
  },
  {
    "end_ms": 55473,
    "start_ms": 55043,
    "word": "কেবল"
  },
  {
    "end_ms": 55688,
    "start_ms": 55473,
    "word": "ঘর"
  },
  {
    "end_ms": 56011,
    "start_ms": 55688,
    "word": "কতক"
  },
  {
    "end_ms": 57086,
    "start_ms": 56011,
    "word": "কৈবর্ত্তের"
  },
  {
    "end_ms": 57409,
    "start_ms": 57086,
    "word": "বাস"
  },
  {
    "end_ms": 57839,
    "start_ms": 57409,
    "word": "গুড়"
  },
  {
    "end_ms": 58484,
    "start_ms": 57839,
    "word": "মহাশয়"
  },
  {
    "end_ms": 59667,
    "start_ms": 58484,
    "word": "মোনাপাড়ায়"
  },
  {
    "end_ms": 60420,
    "start_ms": 59667,
    "word": "একমাত্র"
  },
  {
    "end_ms": 61280,
    "start_ms": 60420,
    "word": "ব্রাহ্মণ"
  },
  {
    "end_ms": 61711,
    "start_ms": 61280,
    "word": "যেমন"
  },
  {
    "end_ms": 61926,
    "start_ms": 61711,
    "word": "এক"
  },
  {
    "end_ms": 62571,
    "start_ms": 61926,
    "word": "চন্দ্র"
  },
  {
    "end_ms": 63001,
    "start_ms": 62571,
    "word": "রজনী"
  },
  {
    "end_ms": 63862,
    "start_ms": 63001,
    "word": "আলোকময়ী"
  },
  {
    "end_ms": 64292,
    "start_ms": 63862,
    "word": "করেন"
  },
  {
    "end_ms": 64722,
    "start_ms": 64292,
    "word": "যেমন"
  },
  {
    "end_ms": 64937,
    "start_ms": 64722,
    "word": "এক"
  },
  {
    "end_ms": 65797,
    "start_ms": 64937,
    "word": "সূর্য্যই"
  },
  {
    "end_ms": 66443,
    "start_ms": 65797,
    "word": "দিনমণি"
  },
  {
    "end_ms": 66873,
    "start_ms": 66443,
    "word": "যেমন"
  },
  {
    "end_ms": 67088,
    "start_ms": 66873,
    "word": "এক"
  },
  {
    "end_ms": 68594,
    "start_ms": 67088,
    "word": "বার্ত্তাকুদগ্ধ"
  },
  {
    "end_ms": 69024,
    "start_ms": 68594,
    "word": "গুড়"
  },
  {
    "end_ms": 69884,
    "start_ms": 69024,
    "word": "মহাশয়ের"
  },
  {
    "end_ms": 70852,
    "start_ms": 69884,
    "word": "অন্নরাশির"
  },
  {
    "end_ms": 71175,
    "start_ms": 70852,
    "word": "উপর"
  },
  {
    "end_ms": 71605,
    "start_ms": 71175,
    "word": "শোভা"
  },
  {
    "end_ms": 72250,
    "start_ms": 71605,
    "word": "করিতেন"
  },
  {
    "end_ms": 72788,
    "start_ms": 72250,
    "word": "তেমনি"
  },
  {
    "end_ms": 73541,
    "start_ms": 72788,
    "word": "সাফলরাম"
  },
  {
    "end_ms": 73756,
    "start_ms": 73541,
    "word": "এক"
  },
  {
    "end_ms": 74616,
    "start_ms": 73756,
    "word": "ব্রাহ্মণ"
  },
  {
    "end_ms": 75584,
    "start_ms": 74616,
    "word": "মোহনপল্লী"
  },
  {
    "end_ms": 76337,
    "start_ms": 75584,
    "word": "উজ্জ্বল"
  },
  {
    "end_ms": 76982,
    "start_ms": 76337,
    "word": "করিতেন"
  },
  {
    "end_ms": 78595,
    "start_ms": 76982,
    "word": "শ্রাদ্ধশান্তিতে"
  },
  {
    "end_ms": 79133,
    "start_ms": 78595,
    "word": "কাঁচা"
  },
  {
    "end_ms": 79563,
    "start_ms": 79133,
    "word": "পাকা"
  },
  {
    "end_ms": 79993,
    "start_ms": 79563,
    "word": "কদলী"
  },
  {
    "end_ms": 80316,
    "start_ms": 79993,
    "word": "আতপ"
  },
  {
    "end_ms": 80961,
    "start_ms": 80316,
    "word": "তণ্ডুল"
  },
  {
    "end_ms": 81284,
    "start_ms": 80961,
    "word": "এবং"
  },
  {
    "end_ms": 82037,
    "start_ms": 81284,
    "word": "দক্ষিণা"
  },
  {
    "end_ms": 82575,
    "start_ms": 82037,
    "word": "ষষ্ঠী"
  },
  {
    "end_ms": 83327,
    "start_ms": 82575,
    "word": "মাকালের"
  },
  {
    "end_ms": 83973,
    "start_ms": 83327,
    "word": "পূজায়"
  },
  {
    "end_ms": 85586,
    "start_ms": 83973,
    "word": "অন্নপ্রাশনাদিতে"
  },
  {
    "end_ms": 86339,
    "start_ms": 85586,
    "word": "নারিকেল"
  },
  {
    "end_ms": 86876,
    "start_ms": 86339,
    "word": "নাড়ু"
  },
  {
    "end_ms": 87307,
    "start_ms": 86876,
    "word": "ছোলা"
  },
  {
    "end_ms": 87629,
    "start_ms": 87307,
    "word": "কলা"
  },
  {
    "end_ms": 87952,
    "start_ms": 87629,
    "word": "আদি"
  },
  {
    "end_ms": 88597,
    "start_ms": 87952,
    "word": "তাঁহার"
  },
  {
    "end_ms": 88920,
    "start_ms": 88597,
    "word": "লাভ"
  },
  {
    "end_ms": 89242,
    "start_ms": 88920,
    "word": "হইত"
  },
  {
    "end_ms": 89888,
    "start_ms": 89242,
    "word": "সুতরাং"
  },
  {
    "end_ms": 91286,
    "start_ms": 89888,
    "word": "যাজনক্রিয়ায়"
  },
  {
    "end_ms": 91931,
    "start_ms": 91286,
    "word": "তাঁহার"
  },
  {
    "end_ms": 92469,
    "start_ms": 91931,
    "word": "বিশেষ"
  },
  {
    "end_ms": 93114,
    "start_ms": 92469,
    "word": "মনোযোগ"
  },
  {
    "end_ms": 93437,
    "start_ms": 93114,
    "word": "ছিল"
  },
  {
    "end_ms": 94189,
    "start_ms": 93437,
    "word": "তাঁহারই"
  },
  {
    "end_ms": 95372,
    "start_ms": 94189,
    "word": "ঐশ্বর্য্যের"
  },
  {
    "end_ms": 96663,
    "start_ms": 95372,
    "word": "উত্তরাধিকারী"
  },
  {
    "end_ms": 96986,
    "start_ms": 96663,
    "word": "এবং"
  },
  {
    "end_ms": 97954,
    "start_ms": 96986,
    "word": "তদর্জ্জিত"
  },
  {
    "end_ms": 99137,
    "start_ms": 97954,
    "word": "রম্ভাভোজনের"
  },
  {
    "end_ms": 99782,
    "start_ms": 99137,
    "word": "হক্দার"
  },
  {
    "end_ms": 100320,
    "start_ms": 99782,
    "word": "হইয়া"
  },
  {
    "end_ms": 101072,
    "start_ms": 100320,
    "word": "মুচিরাম"
  },
  {
    "end_ms": 101933,
    "start_ms": 101072,
    "word": "শুভক্ষণে"
  },
  {
    "end_ms": 102901,
    "start_ms": 101933,
    "word": "জন্মগ্রহণ"
  },
  {
    "end_ms": 103546,
    "start_ms": 102901,
    "word": "করিলেন"
  },
  {
    "end_ms": 104729,
    "start_ms": 103546,
    "word": "জন্মগ্রহণের"
  },
  {
    "end_ms": 104944,
    "start_ms": 104729,
    "word": "পর"
  },
  {
    "end_ms": 105697,
    "start_ms": 104944,
    "word": "মুচিরাম"
  },
  {
    "end_ms": 106127,
    "start_ms": 105697,
    "word": "দিনে"
  },
  {
    "end_ms": 106557,
    "start_ms": 106127,
    "word": "দিনে"
  },
  {
    "end_ms": 107310,
    "start_ms": 106557,
    "word": "বাড়িতে"
  },
  {
    "end_ms": 108063,
    "start_ms": 107310,
    "word": "লাগিলেন"
  },
  {
    "end_ms": 108816,
    "start_ms": 108063,
    "word": "দেখিয়া"
  },
  {
    "end_ms": 109353,
    "start_ms": 108816,
    "word": "যশোদা"
  },
  {
    "end_ms": 109784,
    "start_ms": 109353,
    "word": "সেটা"
  },
  {
    "end_ms": 110429,
    "start_ms": 109784,
    "word": "বালকের"
  },
  {
    "end_ms": 111182,
    "start_ms": 110429,
    "word": "অসাধারণ"
  },
  {
    "end_ms": 111935,
    "start_ms": 111182,
    "word": "পৌরুষের"
  },
  {
    "end_ms": 112472,
    "start_ms": 111935,
    "word": "লক্ষণ"
  },
  {
    "end_ms": 113225,
    "start_ms": 112472,
    "word": "বিবেচনা"
  },
  {
    "end_ms": 113870,
    "start_ms": 113225,
    "word": "করিয়া"
  },
  {
    "end_ms": 114516,
    "start_ms": 113870,
    "word": "অতিশয়"
  },
  {
    "end_ms": 115914,
    "start_ms": 114516,
    "word": "গর্ব্বান্বিতা"
  },
  {
    "end_ms": 116451,
    "start_ms": 115914,
    "word": "হইলেন"
  },
  {
    "end_ms": 117204,
    "start_ms": 116451,
    "word": "যথাকালে"
  },
  {
    "end_ms": 118172,
    "start_ms": 117204,
    "word": "মুচিরামের"
  },
  {
    "end_ms": 119248,
    "start_ms": 118172,
    "word": "অন্নপ্রাশন"
  },
  {
    "end_ms": 119570,
    "start_ms": 119248,
    "word": "হইল"
  },
  {
    "end_ms": 120216,
    "start_ms": 119570,
    "word": "নামকরণ"
  },
  {
    "end_ms": 120538,
    "start_ms": 120216,
    "word": "হইল"
  },
  {
    "end_ms": 121291,
    "start_ms": 120538,
    "word": "মুচিরাম"
  },
  {
    "end_ms": 121506,
    "start_ms": 121291,
    "word": "এত"
  },
  {
    "end_ms": 122366,
    "start_ms": 121506,
    "word": "নগেন্দ্র"
  },
  {
    "end_ms": 123227,
    "start_ms": 122366,
    "word": "গজেন্দ্র"
  },
  {
    "end_ms": 124302,
    "start_ms": 123227,
    "word": "চন্দ্রভূষণ"
  },
  {
    "end_ms": 125163,
    "start_ms": 124302,
    "word": "বিধুভূষণ"
  },
  {
    "end_ms": 125808,
    "start_ms": 125163,
    "word": "থাকিতে"
  },
  {
    "end_ms": 126453,
    "start_ms": 125808,
    "word": "তাঁহার"
  },
  {
    "end_ms": 127206,
    "start_ms": 126453,
    "word": "মুচিরাম"
  },
  {
    "end_ms": 127529,
    "start_ms": 127206,
    "word": "নাম"
  },
  {
    "end_ms": 127851,
    "start_ms": 127529,
    "word": "হইল"
  },
  {
    "end_ms": 128174,
    "start_ms": 127851,
    "word": "কেন"
  },
  {
    "end_ms": 128604,
    "start_ms": 128174,
    "word": "তাহা"
  },
  {
    "end_ms": 128927,
    "start_ms": 128604,
    "word": "আমি"
  },
  {
    "end_ms": 129572,
    "start_ms": 128927,
    "word": "সবিশেষ"
  },
  {
    "end_ms": 130002,
    "start_ms": 129572,
    "word": "জানি"
  },
  {
    "end_ms": 130217,
    "start_ms": 130002,
    "word": "না"
  },
  {
    "end_ms": 130540,
    "start_ms": 130217,
    "word": "তবে"
  },
  {
    "end_ms": 131078,
    "start_ms": 130540,
    "word": "দুষ্ট"
  },
  {
    "end_ms": 131508,
    "start_ms": 131078,
    "word": "লোকে"
  },
  {
    "end_ms": 131938,
    "start_ms": 131508,
    "word": "বলিত"
  },
  {
    "end_ms": 132153,
    "start_ms": 131938,
    "word": "যে"
  },
  {
    "end_ms": 132691,
    "start_ms": 132153,
    "word": "যশোদা"
  },
  {
    "end_ms": 133229,
    "start_ms": 132691,
    "word": "দেবীর"
  },
  {
    "end_ms": 134089,
    "start_ms": 133229,
    "word": "যৌবনকালে"
  },
  {
    "end_ms": 134412,
    "start_ms": 134089,
    "word": "কোন"
  },
  {
    "end_ms": 134842,
    "start_ms": 134412,
    "word": "কালো"
  },
  {
    "end_ms": 135272,
    "start_ms": 134842,
    "word": "কোলো"
  },
  {
    "end_ms": 136455,
    "start_ms": 135272,
    "word": "কোঁক্ড়াচুল"
  },
  {
    "end_ms": 137208,
    "start_ms": 136455,
    "word": "নধরশরীর"
  },
  {
    "end_ms": 137961,
    "start_ms": 137208,
    "word": "মুচিরাম"
  },
  {
    "end_ms": 138283,
    "start_ms": 137961,
    "word": "দাস"
  },
  {
    "end_ms": 138713,
    "start_ms": 138283,
    "word": "নামা"
  },
  {
    "end_ms": 140112,
    "start_ms": 138713,
    "word": "কৈবর্ত্তপুত্র"
  },
  {
    "end_ms": 140757,
    "start_ms": 140112,
    "word": "তাঁহার"
  },
  {
    "end_ms": 141617,
    "start_ms": 140757,
    "word": "নয়নপথের"
  },
  {
    "end_ms": 142047,
    "start_ms": 141617,
    "word": "পথিক"
  },
  {
    "end_ms": 142908,
    "start_ms": 142047,
    "word": "হইয়াছিল"
  },
  {
    "end_ms": 143230,
    "start_ms": 142908,
    "word": "সেই"
  },
  {
    "end_ms": 143661,
    "start_ms": 143230,
    "word": "অবধি"
  },
  {
    "end_ms": 144413,
    "start_ms": 143661,
    "word": "মুচিরাম"
  },
  {
    "end_ms": 144951,
    "start_ms": 144413,
    "word": "নামটি"
  },
  {
    "end_ms": 145596,
    "start_ms": 144951,
    "word": "যশোদার"
  },
  {
    "end_ms": 146027,
    "start_ms": 145596,
    "word": "কাণে"
  },
  {
    "end_ms": 146564,
    "start_ms": 146027,
    "word": "মিষ্ট"
  },
  {
    "end_ms": 147102,
    "start_ms": 146564,
    "word": "লাগিত"
  },
  {
    "end_ms": 147640,
    "start_ms": 147102,
    "word": "যাহাই"
  },
  {
    "end_ms": 147962,
    "start_ms": 147640,
    "word": "হউক"
  },
  {
    "end_ms": 148500,
    "start_ms": 147962,
    "word": "যশোদা"
  },
  {
    "end_ms": 148823,
    "start_ms": 148500,
    "word": "নাম"
  },
  {
    "end_ms": 149576,
    "start_ms": 148823,
    "word": "রাখিলেন"
  },
  {
    "end_ms": 150328,
    "start_ms": 149576,
    "word": "মুচিরাম"
  },
  {
    "end_ms": 150651,
    "start_ms": 150328,
    "word": "নাম"
  },
  {
    "end_ms": 151296,
    "start_ms": 150651,
    "word": "পাইয়া"
  },
  {
    "end_ms": 152049,
    "start_ms": 151296,
    "word": "মুচিরাম"
  },
  {
    "end_ms": 152802,
    "start_ms": 152049,
    "word": "শর্ম্মা"
  },
  {
    "end_ms": 153232,
    "start_ms": 152802,
    "word": "দিনে"
  },
  {
    "end_ms": 153662,
    "start_ms": 153232,
    "word": "দিনে"
  },
  {
    "end_ms": 154415,
    "start_ms": 153662,
    "word": "বাড়িতে"
  },
  {
    "end_ms": 155168,
    "start_ms": 154415,
    "word": "লাগিলেন"
  },
  {
    "end_ms": 155706,
    "start_ms": 155168,
    "word": "ক্রমে"
  },
  {
    "end_ms": 155921,
    "start_ms": 155706,
    "word": "মা"
  },
  {
    "end_ms": 156351,
    "start_ms": 155921,
    "word": "বাবা"
  },
  {
    "end_ms": 156566,
    "start_ms": 156351,
    "word": "দু"
  },
  {
    "end_ms": 156781,
    "start_ms": 156566,
    "word": "দে"
  },
  {
    "end_ms": 157534,
    "start_ms": 156781,
    "word": "ইত্যাদি"
  },
  {
    "end_ms": 157964,
    "start_ms": 157534,
    "word": "শব্দ"
  },
  {
    "end_ms": 158717,
    "start_ms": 157964,
    "word": "উচ্চারণ"
  },
  {
    "end_ms": 159255,
    "start_ms": 158717,
    "word": "করিতে"
  },
  {
    "end_ms": 160008,
    "start_ms": 159255,
    "word": "শিখিলেন"
  },
  {
    "end_ms": 160670,
    "start_ms": 160008,
    "word": "তাঁহার"
  },
  {
    "end_ms": 161442,
    "start_ms": 160670,
    "word": "অসাধারণ"
  },
  {
    "end_ms": 162326,
    "start_ms": 161442,
    "word": "ধীশক্তির"
  },
  {
    "end_ms": 162657,
    "start_ms": 162326,
    "word": "বলে"
  },
  {
    "end_ms": 163981,
    "start_ms": 162657,
    "word": "মিছাকান্নায়"
  },
  {
    "end_ms": 164202,
    "start_ms": 163981,
    "word": "এক"
  },
  {
    "end_ms": 164644,
    "start_ms": 164202,
    "word": "বৎসর"
  },
  {
    "end_ms": 164975,
    "start_ms": 164644,
    "word": "পার"
  },
  {
    "end_ms": 165416,
    "start_ms": 164975,
    "word": "হইতে"
  },
  {
    "end_ms": 165637,
    "start_ms": 165416,
    "word": "না"
  },
  {
    "end_ms": 166189,
    "start_ms": 165637,
    "word": "হইতেই"
  },
  {
    "end_ms": 167072,
    "start_ms": 166189,
    "word": "সুপণ্ডিত"
  },
  {
    "end_ms": 167624,
    "start_ms": 167072,
    "word": "হইলেন"
  },
  {
    "end_ms": 167955,
    "start_ms": 167624,
    "word": "তিন"
  },
  {
    "end_ms": 168397,
    "start_ms": 167955,
    "word": "বৎসর"
  },
  {
    "end_ms": 168949,
    "start_ms": 168397,
    "word": "যাইতে"
  },
  {
    "end_ms": 169169,
    "start_ms": 168949,
    "word": "না"
  },
  {
    "end_ms": 169832,
    "start_ms": 169169,
    "word": "যাইতেই"
  },
  {
    "end_ms": 170825,
    "start_ms": 169832,
    "word": "গুরুভোজনে"
  },
  {
    "end_ms": 171156,
    "start_ms": 170825,
    "word": "দোষ"
  },
  {
    "end_ms": 171929,
    "start_ms": 171156,
    "word": "উপস্থিত"
  },
  {
    "end_ms": 172260,
    "start_ms": 171929,
    "word": "হইল"
  },
  {
    "end_ms": 172591,
    "start_ms": 172260,
    "word": "এবং"
  },
  {
    "end_ms": 173033,
    "start_ms": 172591,
    "word": "পাঁচ"
  },
  {
    "end_ms": 173474,
    "start_ms": 173033,
    "word": "বৎসর"
  },
  {
    "end_ms": 174026,
    "start_ms": 173474,
    "word": "যাইতে"
  },
  {
    "end_ms": 174247,
    "start_ms": 174026,
    "word": "না"
  },
  {
    "end_ms": 174909,
    "start_ms": 174247,
    "word": "যাইতেই"
  },
  {
    "end_ms": 175572,
    "start_ms": 174909,
    "word": "মহামতি"
  },
  {
    "end_ms": 176344,
    "start_ms": 175572,
    "word": "মুচিরাম"
  },
  {
    "end_ms": 176786,
    "start_ms": 176344,
    "word": "মাকে"
  },
  {
    "end_ms": 177227,
    "start_ms": 176786,
    "word": "পিতৃ"
  },
  {
    "end_ms": 178000,
    "start_ms": 177227,
    "word": "উচ্চারণ"
  },
  {
    "end_ms": 178552,
    "start_ms": 178000,
    "word": "করিতে"
  },
  {
    "end_ms": 178883,
    "start_ms": 178552,
    "word": "এবং"
  },
  {
    "end_ms": 179435,
    "start_ms": 178883,
    "word": "বাপকে"
  },
  {
    "end_ms": 179876,
    "start_ms": 179435,
    "word": "শালা"
  },
  {
    "end_ms": 180428,
    "start_ms": 179876,
    "word": "বলিতে"
  },
  {
    "end_ms": 181201,
    "start_ms": 180428,
    "word": "শিখিলেন"
  },
  {
    "end_ms": 181753,
    "start_ms": 181201,
    "word": "যশোদা"
  },
  {
    "end_ms": 182636,
    "start_ms": 181753,
    "word": "কাঁদিয়া"
  },
  {
    "end_ms": 183298,
    "start_ms": 182636,
    "word": "বলিতেন"
  },
  {
    "end_ms": 183629,
    "start_ms": 183298,
    "word": "এমন"
  },
  {
    "end_ms": 184181,
    "start_ms": 183629,
    "word": "গুণের"
  },
  {
    "end_ms": 184623,
    "start_ms": 184181,
    "word": "ছেলে"
  },
  {
    "end_ms": 185396,
    "start_ms": 184623,
    "word": "বাঁচ্লে"
  },
  {
    "end_ms": 185727,
    "start_ms": 185396,
    "word": "হয়"
  },
  {
    "end_ms": 186168,
    "start_ms": 185727,
    "word": "পাঁচ"
  },
  {
    "end_ms": 186720,
    "start_ms": 186168,
    "word": "বৎসরে"
  },
  {
    "end_ms": 187493,
    "start_ms": 186720,
    "word": "সাফলরাম"
  },
  {
    "end_ms": 187934,
    "start_ms": 187493,
    "word": "গুড়"
  },
  {
    "end_ms": 188597,
    "start_ms": 187934,
    "word": "মহাশয়"
  },
  {
    "end_ms": 189038,
    "start_ms": 188597,
    "word": "কিছু"
  },
  {
    "end_ms": 189480,
    "start_ms": 189038,
    "word": "গোলে"
  },
  {
    "end_ms": 190252,
    "start_ms": 189480,
    "word": "পড়িলেন"
  },
  {
    "end_ms": 190804,
    "start_ms": 190252,
    "word": "যশোদা"
  },
  {
    "end_ms": 191798,
    "start_ms": 190804,
    "word": "ঠাকুরাণীর"
  },
  {
    "end_ms": 192129,
    "start_ms": 191798,
    "word": "সাধ"
  },
  {
    "end_ms": 192570,
    "start_ms": 192129,
    "word": "পাঁচ"
  },
  {
    "end_ms": 193122,
    "start_ms": 192570,
    "word": "বৎসরে"
  },
  {
    "end_ms": 193895,
    "start_ms": 193122,
    "word": "পুত্রের"
  },
  {
    "end_ms": 194337,
    "start_ms": 193895,
    "word": "হাতে"
  },
  {
    "end_ms": 194778,
    "start_ms": 194337,
    "word": "খড়ি"
  },
  {
    "end_ms": 195109,
    "start_ms": 194778,
    "word": "হয়"
  },
  {
    "end_ms": 196103,
    "start_ms": 195109,
    "word": "সর্ব্বনাশ"
  },
  {
    "end_ms": 197096,
    "start_ms": 196103,
    "word": "সাফলরামের"
  },
  {
    "end_ms": 197427,
    "start_ms": 197096,
    "word": "তিন"
  },
  {
    "end_ms": 198200,
    "start_ms": 197427,
    "word": "পুরুষের"
  },
  {
    "end_ms": 198752,
    "start_ms": 198200,
    "word": "মধ্যে"
  },
  {
    "end_ms": 198973,
    "start_ms": 198752,
    "word": "সে"
  },
  {
    "end_ms": 199304,
    "start_ms": 198973,
    "word": "কাজ"
  },
  {
    "end_ms": 199635,
    "start_ms": 199304,
    "word": "হয়"
  },
  {
    "end_ms": 199966,
    "start_ms": 199635,
    "word": "নাই"
  },
  {
    "end_ms": 200408,
    "start_ms": 199966,
    "word": "মাগী"
  },
  {
    "end_ms": 200739,
    "start_ms": 200408,
    "word": "বলে"
  },
  {
    "end_ms": 200960,
    "start_ms": 200739,
    "word": "কি"
  },
  {
    "end_ms": 201180,
    "start_ms": 200960,
    "word": "যে"
  },
  {
    "end_ms": 201512,
    "start_ms": 201180,
    "word": "দিন"
  },
  {
    "end_ms": 201843,
    "start_ms": 201512,
    "word": "কথা"
  },
  {
    "end_ms": 202395,
    "start_ms": 201843,
    "word": "পড়িল"
  },
  {
    "end_ms": 202615,
    "start_ms": 202395,
    "word": "সে"
  },
  {
    "end_ms": 202947,
    "start_ms": 202615,
    "word": "দিন"
  },
  {
    "end_ms": 203940,
    "start_ms": 202947,
    "word": "সাফলরামের"
  },
  {
    "end_ms": 204602,
    "start_ms": 203940,
    "word": "নিদ্রা"
  },
  {
    "end_ms": 204933,
    "start_ms": 204602,
    "word": "হইল"
  },
  {
    "end_ms": 205154,
    "start_ms": 204933,
    "word": "না"
  },
  {
    "end_ms": 205816,
    "start_ms": 205154,
    "word": "যমুনার"
  },
  {
    "end_ms": 206037,
    "start_ms": 205816,
    "word": "জল"
  },
  {
    "end_ms": 206479,
    "start_ms": 206037,
    "word": "উজান"
  },
  {
    "end_ms": 207031,
    "start_ms": 206479,
    "word": "বহিতে"
  },
  {
    "end_ms": 207472,
    "start_ms": 207031,
    "word": "পারে"
  },
  {
    "end_ms": 207803,
    "start_ms": 207472,
    "word": "তবু"
  },
  {
    "end_ms": 208576,
    "start_ms": 207803,
    "word": "গৃহিণীর"
  },
  {
    "end_ms": 209128,
    "start_ms": 208576,
    "word": "বাক্য"
  },
  {
    "end_ms": 209790,
    "start_ms": 209128,
    "word": "নড়িতে"
  },
  {
    "end_ms": 210232,
    "start_ms": 209790,
    "word": "পারে"
  },
  {
    "end_ms": 210453,
    "start_ms": 210232,
    "word": "না"
  },
  {
    "end_ms": 211115,
    "start_ms": 210453,
    "word": "সুতরাং"
  },
  {
    "end_ms": 211888,
    "start_ms": 211115,
    "word": "সাফলরাম"
  },
  {
    "end_ms": 212329,
    "start_ms": 211888,
    "word": "হাতে"
  },
  {
    "end_ms": 212881,
    "start_ms": 212329,
    "word": "খড়ির"
  },
  {
    "end_ms": 213543,
    "start_ms": 212881,
    "word": "উদ্যোগ"
  },
  {
    "end_ms": 214206,
    "start_ms": 213543,
    "word": "দেখিতে"
  },
  {
    "end_ms": 214978,
    "start_ms": 214206,
    "word": "লাগিলেন"
  },
  {
    "end_ms": 215641,
    "start_ms": 214978,
    "word": "কিন্তু"
  },
  {
    "end_ms": 217076,
    "start_ms": 215641,
    "word": "দুর্ভাগ্যবশতঃ"
  },
  {
    "end_ms": 217407,
    "start_ms": 217076,
    "word": "তিন"
  },
  {
    "end_ms": 218179,
    "start_ms": 217407,
    "word": "ক্রোশের"
  },
  {
    "end_ms": 218731,
    "start_ms": 218179,
    "word": "মধ্যে"
  },
  {
    "end_ms": 219504,
    "start_ms": 218731,
    "word": "পাঠশালা"
  },
  {
    "end_ms": 219725,
    "start_ms": 219504,
    "word": "বা"
  },
  {
    "end_ms": 220166,
    "start_ms": 219725,
    "word": "গুরু"
  },
  {
    "end_ms": 220829,
    "start_ms": 220166,
    "word": "মহাশয়"
  },
  {
    "end_ms": 221160,
    "start_ms": 220829,
    "word": "নাই"
  },
  {
    "end_ms": 221380,
    "start_ms": 221160,
    "word": "কে"
  },
  {
    "end_ms": 222264,
    "start_ms": 221380,
    "word": "লেখাপড়া"
  },
  {
    "end_ms": 223036,
    "start_ms": 222264,
    "word": "শিখাইবে"
  },
  {
    "end_ms": 223809,
    "start_ms": 223036,
    "word": "সাফলরাম"
  },
  {
    "end_ms": 224913,
    "start_ms": 223809,
    "word": "বিষণ্নবদনে"
  },
  {
    "end_ms": 225906,
    "start_ms": 224913,
    "word": "বিনীতভাবে"
  },
  {
    "end_ms": 226458,
    "start_ms": 225906,
    "word": "যশোদা"
  },
  {
    "end_ms": 227010,
    "start_ms": 226458,
    "word": "দেবীর"
  },
  {
    "end_ms": 228335,
    "start_ms": 227010,
    "word": "শ্রীপাদপদ্মে"
  },
  {
    "end_ms": 228555,
    "start_ms": 228335,
    "word": "এই"
  },
  {
    "end_ms": 229218,
    "start_ms": 228555,
    "word": "সম্বাদ"
  },
  {
    "end_ms": 230211,
    "start_ms": 229218,
    "word": "সুনিবেদিত"
  },
  {
    "end_ms": 230763,
    "start_ms": 230211,
    "word": "হইলেন"
  },
  {
    "end_ms": 231315,
    "start_ms": 230763,
    "word": "যশোদা"
  },
  {
    "end_ms": 231977,
    "start_ms": 231315,
    "word": "বলিলেন"
  },
  {
    "end_ms": 232308,
    "start_ms": 231977,
    "word": "ভাল"
  },
  {
    "end_ms": 232750,
    "start_ms": 232308,
    "word": "তুমি"
  },
  {
    "end_ms": 233081,
    "start_ms": 232750,
    "word": "কেন"
  },
  {
    "end_ms": 233633,
    "start_ms": 233081,
    "word": "আপনিই"
  },
  {
    "end_ms": 234075,
    "start_ms": 233633,
    "word": "হাতে"
  },
  {
    "end_ms": 234516,
    "start_ms": 234075,
    "word": "খড়ি"
  },
  {
    "end_ms": 235068,
    "start_ms": 234516,
    "word": "দিয়া"
  },
  {
    "end_ms": 235178,
    "start_ms": 235068,
    "word": "ক"
  },
  {
    "end_ms": 235289,
    "start_ms": 235178,
    "word": "খ"
  },
  {
    "end_ms": 235841,
    "start_ms": 235289,
    "word": "শিখাও"
  },
  {
    "end_ms": 236061,
    "start_ms": 235841,
    "word": "না"
  },
  {
    "end_ms": 236834,
    "start_ms": 236061,
    "word": "সাফলরাম"
  },
  {
    "end_ms": 237276,
    "start_ms": 236834,
    "word": "একটু"
  },
  {
    "end_ms": 237828,
    "start_ms": 237276,
    "word": "ম্লান"
  },
  {
    "end_ms": 238379,
    "start_ms": 237828,
    "word": "হইয়া"
  },
  {
    "end_ms": 239042,
    "start_ms": 238379,
    "word": "বলিলেন"
  },
  {
    "end_ms": 239373,
    "start_ms": 239042,
    "word": "হাঁ"
  },
  {
    "end_ms": 239594,
    "start_ms": 239373,
    "word": "তা"
  },
  {
    "end_ms": 239925,
    "start_ms": 239594,
    "word": "আমি"
  },
  {
    "end_ms": 240366,
    "start_ms": 239925,
    "word": "পারি"
  },
  {
    "end_ms": 240698,
    "start_ms": 240366,
    "word": "তবে"
  },
  {
    "end_ms": 240918,
    "start_ms": 240698,
    "word": "কি"
  },
  {
    "end_ms": 241249,
    "start_ms": 240918,
    "word": "জান"
  },
  {
    "end_ms": 242243,
    "start_ms": 241249,
    "word": "শিষ্যসেবক"
  },
  {
    "end_ms": 243016,
    "start_ms": 242243,
    "word": "যজমানের"
  },
  {
    "end_ms": 243899,
    "start_ms": 243016,
    "word": "জ্বালায়"
  },
  {
    "end_ms": 244230,
    "start_ms": 243899,
    "word": "আজি"
  },
  {
    "end_ms": 244451,
    "start_ms": 244230,
    "word": "কি"
  },
  {
    "end_ms": 245113,
    "start_ms": 244451,
    "word": "রান্না"
  },
  {
    "end_ms": 245444,
    "start_ms": 245113,
    "word": "হইল"
  },
  {
    "end_ms": 246658,
    "start_ms": 245444,
    "word": "শুনিবামাত্র"
  },
  {
    "end_ms": 247210,
    "start_ms": 246658,
    "word": "যশোদা"
  },
  {
    "end_ms": 247762,
    "start_ms": 247210,
    "word": "দেবীর"
  },
  {
    "end_ms": 248093,
    "start_ms": 247762,
    "word": "মনে"
  },
  {
    "end_ms": 248645,
    "start_ms": 248093,
    "word": "পড়িল"
  },
  {
    "end_ms": 248976,
    "start_ms": 248645,
    "word": "আজি"
  },
  {
    "end_ms": 250190,
    "start_ms": 248976,
    "word": "কৈবর্ত্তেরা"
  },
  {
    "end_ms": 251074,
    "start_ms": 250190,
    "word": "পাতিলেবু"
  },
  {
    "end_ms": 251625,
    "start_ms": 251074,
    "word": "দিয়া"
  },
  {
    "end_ms": 252398,
    "start_ms": 251625,
    "word": "গিয়াছে"
  },
  {
    "end_ms": 253060,
    "start_ms": 252398,
    "word": "বলিলেন"
  },
  {
    "end_ms": 253833,
    "start_ms": 253060,
    "word": "অধঃপেতে"
  },
  {
    "end_ms": 254495,
    "start_ms": 253833,
    "word": "মিন্সে"
  },
  {
    "end_ms": 254716,
    "start_ms": 254495,
    "word": "এই"
  },
  {
    "end_ms": 255378,
    "start_ms": 254716,
    "word": "বলিয়া"
  },
  {
    "end_ms": 256924,
    "start_ms": 255378,
    "word": "পতিপুত্রপ্রাণা"
  },
  {
    "end_ms": 257476,
    "start_ms": 256924,
    "word": "যশোদা"
  },
  {
    "end_ms": 257917,
    "start_ms": 257476,
    "word": "দেবী"
  },
  {
    "end_ms": 258911,
    "start_ms": 257917,
    "word": "বিষণ্নমনে"
  },
  {
    "end_ms": 259794,
    "start_ms": 258911,
    "word": "সজলনয়নে"
  },
  {
    "end_ms": 260677,
    "start_ms": 259794,
    "word": "পাতিলেবু"
  },
  {
    "end_ms": 261229,
    "start_ms": 260677,
    "word": "দিয়া"
  },
  {
    "end_ms": 261891,
    "start_ms": 261229,
    "word": "পান্তা"
  },
  {
    "end_ms": 262222,
    "start_ms": 261891,
    "word": "ভাত"
  },
  {
    "end_ms": 262774,
    "start_ms": 262222,
    "word": "খাইতে"
  },
  {
    "end_ms": 263436,
    "start_ms": 262774,
    "word": "বসিলেন"
  },
  {
    "end_ms": 264099,
    "start_ms": 263436,
    "word": "অগত্যা"
  },
  {
    "end_ms": 264871,
    "start_ms": 264099,
    "word": "মুচিরাম"
  },
  {
    "end_ms": 265754,
    "start_ms": 264871,
    "word": "অন্যান্য"
  },
  {
    "end_ms": 266417,
    "start_ms": 265754,
    "word": "বিদ্যা"
  },
  {
    "end_ms": 267189,
    "start_ms": 266417,
    "word": "অভ্যাসে"
  },
  {
    "end_ms": 267962,
    "start_ms": 267189,
    "word": "সানুরাগ"
  },
  {
    "end_ms": 268514,
    "start_ms": 267962,
    "word": "হইলেন"
  },
  {
    "end_ms": 269397,
    "start_ms": 268514,
    "word": "অন্যান্য"
  },
  {
    "end_ms": 270170,
    "start_ms": 269397,
    "word": "বিদ্যার"
  },
  {
    "end_ms": 270722,
    "start_ms": 270170,
    "word": "মধ্যে"
  },
  {
    "end_ms": 271053,
    "start_ms": 270722,
    "word": "পরা"
  },
  {
    "end_ms": 271494,
    "start_ms": 271053,
    "word": "অপরা"
  },
  {
    "end_ms": 271605,
    "start_ms": 271494,
    "word": "চ"
  },
  {
    "end_ms": 272046,
    "start_ms": 271605,
    "word": "গাছে"
  },
  {
    "end_ms": 272377,
    "start_ms": 272046,
    "word": "ওঠা"
  },
  {
    "end_ms": 272709,
    "start_ms": 272377,
    "word": "জলে"
  },
  {
    "end_ms": 273150,
    "start_ms": 272709,
    "word": "ডোবা"
  },
  {
    "end_ms": 273481,
    "start_ms": 273150,
    "word": "এবং"
  },
  {
    "end_ms": 274144,
    "start_ms": 273481,
    "word": "সন্দেশ"
  },
  {
    "end_ms": 274585,
    "start_ms": 274144,
    "word": "চুরি"
  },
  {
    "end_ms": 275468,
    "start_ms": 274585,
    "word": "কৈবর্ত্ত"
  },
  {
    "end_ms": 276572,
    "start_ms": 275468,
    "word": "যজমানদিগের"
  },
  {
    "end_ms": 277345,
    "start_ms": 276572,
    "word": "কল্যাণে"
  },
  {
    "end_ms": 278007,
    "start_ms": 277345,
    "word": "গুড়ের"
  },
  {
    "end_ms": 278338,
    "start_ms": 278007,
    "word": "ঘরে"
  },
  {
    "end_ms": 279221,
    "start_ms": 278338,
    "word": "সন্দেশের"
  },
  {
    "end_ms": 279663,
    "start_ms": 279221,
    "word": "অভাব"
  },
  {
    "end_ms": 279994,
    "start_ms": 279663,
    "word": "নাই"
  },
  {
    "end_ms": 281429,
    "start_ms": 279994,
    "word": "নারিকেলসন্দেশ"
  },
  {
    "end_ms": 281760,
    "start_ms": 281429,
    "word": "এবং"
  },
  {
    "end_ms": 282643,
    "start_ms": 281760,
    "word": "অন্যান্য"
  },
  {
    "end_ms": 282864,
    "start_ms": 282643,
    "word": "যে"
  },
  {
    "end_ms": 283195,
    "start_ms": 282864,
    "word": "সকল"
  },
  {
    "end_ms": 283857,
    "start_ms": 283195,
    "word": "জাতীয়"
  },
  {
    "end_ms": 284740,
    "start_ms": 283857,
    "word": "সন্দেশের"
  },
  {
    "end_ms": 285292,
    "start_ms": 284740,
    "word": "সঙ্গে"
  },
  {
    "end_ms": 285844,
    "start_ms": 285292,
    "word": "ছানার"
  },
  {
    "end_ms": 286617,
    "start_ms": 285844,
    "word": "সাক্ষাৎ"
  },
  {
    "end_ms": 286838,
    "start_ms": 286617,
    "word": "বা"
  },
  {
    "end_ms": 287721,
    "start_ms": 286838,
    "word": "অসাক্ষাৎ"
  },
  {
    "end_ms": 288052,
    "start_ms": 287721,
    "word": "কোন"
  },
  {
    "end_ms": 288714,
    "start_ms": 288052,
    "word": "প্রকার"
  },
  {
    "end_ms": 289487,
    "start_ms": 288714,
    "word": "সম্বন্ধ"
  },
  {
    "end_ms": 289818,
    "start_ms": 289487,
    "word": "নাই"
  },
  {
    "end_ms": 290259,
    "start_ms": 289818,
    "word": "যাহা"
  },
  {
    "end_ms": 291143,
    "start_ms": 290259,
    "word": "সর্ব্বদা"
  },
  {
    "end_ms": 292136,
    "start_ms": 291143,
    "word": "মুচিরামের"
  },
  {
    "end_ms": 292467,
    "start_ms": 292136,
    "word": "ঘরে"
  },
  {
    "end_ms": 293019,
    "start_ms": 292467,
    "word": "থাকিত"
  },
  {
    "end_ms": 293240,
    "start_ms": 293019,
    "word": "সে"
  },
  {
    "end_ms": 293571,
    "start_ms": 293240,
    "word": "সকল"
  },
  {
    "end_ms": 294564,
    "start_ms": 293571,
    "word": "মুচিরামের"
  },
  {
    "end_ms": 295999,
    "start_ms": 294564,
    "word": "বিদ্যাভ্যাসের"
  },
  {
    "end_ms": 296441,
    "start_ms": 295999,
    "word": "কারণ"
  },
  {
    "end_ms": 296772,
    "start_ms": 296441,
    "word": "হইল"
  },
  {
    "end_ms": 297876,
    "start_ms": 296772,
    "word": "কৈবর্ত্তের"
  },
  {
    "end_ms": 298649,
    "start_ms": 297876,
    "word": "ছেলেদের"
  },
  {
    "end_ms": 299201,
    "start_ms": 298649,
    "word": "সঙ্গে"
  },
  {
    "end_ms": 300194,
    "start_ms": 299201,
    "word": "মুচিরামের"
  },
  {
    "end_ms": 300967,
    "start_ms": 300194,
    "word": "প্রত্যহ"
  },
  {
    "end_ms": 301408,
    "start_ms": 300967,
    "word": "একটি"
  },
  {
    "end_ms": 301850,
    "start_ms": 301408,
    "word": "নূতন"
  },
  {
    "end_ms": 302512,
    "start_ms": 301850,
    "word": "কোন্দল"
  },
  {
    "end_ms": 302843,
    "start_ms": 302512,
    "word": "হইত"
  },
  {
    "end_ms": 303285,
    "start_ms": 302843,
    "word": "শুনা"
  },
  {
    "end_ms": 304057,
    "start_ms": 303285,
    "word": "গিয়াছে"
  },
  {
    "end_ms": 305492,
    "start_ms": 304057,
    "word": "কৈবর্ত্তদিগের"
  },
  {
    "end_ms": 305934,
    "start_ms": 305492,
    "word": "ঘরেও"
  },
  {
    "end_ms": 306486,
    "start_ms": 305934,
    "word": "খাবার"
  },
  {
    "end_ms": 306927,
    "start_ms": 306486,
    "word": "চুরি"
  },
  {
    "end_ms": 307369,
    "start_ms": 306927,
    "word": "যাইত"
  },
  {
    "end_ms": 307700,
    "start_ms": 307369,
    "word": "নবম"
  },
  {
    "end_ms": 308252,
    "start_ms": 307700,
    "word": "বৎসরে"
  },
  {
    "end_ms": 309245,
    "start_ms": 308252,
    "word": "মুচিরামের"
  },
  {
    "end_ms": 309908,
    "start_ms": 309245,
    "word": "উপনয়ন"
  },
  {
    "end_ms": 310239,
    "start_ms": 309908,
    "word": "হইল"
  },
  {
    "end_ms": 310570,
    "start_ms": 310239,
    "word": "তার"
  },
  {
    "end_ms": 310791,
    "start_ms": 310570,
    "word": "পর"
  },
  {
    "end_ms": 311563,
    "start_ms": 310791,
    "word": "সাফলরাম"
  },
  {
    "end_ms": 311784,
    "start_ms": 311563,
    "word": "এক"
  },
  {
    "end_ms": 312226,
    "start_ms": 311784,
    "word": "বৎসর"
  },
  {
    "end_ms": 313109,
    "start_ms": 312226,
    "word": "প্রিয়তম"
  },
  {
    "end_ms": 313881,
    "start_ms": 313109,
    "word": "পুত্রকে"
  },
  {
    "end_ms": 314654,
    "start_ms": 313881,
    "word": "সন্ধ্যা"
  },
  {
    "end_ms": 315316,
    "start_ms": 314654,
    "word": "আহ্নিক"
  },
  {
    "end_ms": 316200,
    "start_ms": 315316,
    "word": "শিখাইলেন"
  },
  {
    "end_ms": 316457,
    "start_ms": 316200,
    "word": "এক"
  },
  {
    "end_ms": 317101,
    "start_ms": 316457,
    "word": "বৎসরে"
  },
  {
    "end_ms": 318003,
    "start_ms": 317101,
    "word": "মুচিরাম"
  },
  {
    "end_ms": 318905,
    "start_ms": 318003,
    "word": "সন্ধ্যা"
  },
  {
    "end_ms": 319678,
    "start_ms": 318905,
    "word": "আহ্নিক"
  },
  {
    "end_ms": 321225,
    "start_ms": 319678,
    "word": "শিখিয়াছিলেন"
  },
  {
    "end_ms": 321482,
    "start_ms": 321225,
    "word": "কি"
  },
  {
    "end_ms": 321740,
    "start_ms": 321482,
    "word": "না"
  },
  {
    "end_ms": 322255,
    "start_ms": 321740,
    "word": "আমরা"
  },
  {
    "end_ms": 322771,
    "start_ms": 322255,
    "word": "জানি"
  },
  {
    "end_ms": 323029,
    "start_ms": 322771,
    "word": "না"
  },
  {
    "end_ms": 323415,
    "start_ms": 323029,
    "word": "কেন"
  },
  {
    "end_ms": 323673,
    "start_ms": 323415,
    "word": "না"
  },
  {
    "end_ms": 324961,
    "start_ms": 323673,
    "word": "প্রমাণাভাব"
  },
  {
    "end_ms": 325348,
    "start_ms": 324961,
    "word": "তার"
  },
  {
    "end_ms": 325605,
    "start_ms": 325348,
    "word": "পর"
  },
  {
    "end_ms": 326507,
    "start_ms": 325605,
    "word": "মুচিরাম"
  },
  {
    "end_ms": 326894,
    "start_ms": 326507,
    "word": "কখন"
  },
  {
    "end_ms": 327796,
    "start_ms": 326894,
    "word": "সন্ধ্যা"
  },
  {
    "end_ms": 328569,
    "start_ms": 327796,
    "word": "আহ্নিক"
  },
  {
    "end_ms": 329084,
    "start_ms": 328569,
    "word": "করেন"
  },
  {
    "end_ms": 329471,
    "start_ms": 329084,
    "word": "নাই"
  },
  {
    "end_ms": 330115,
    "start_ms": 329471,
    "word": "তৎপরে"
  },
  {
    "end_ms": 330759,
    "start_ms": 330115,
    "word": "একদিন"
  },
  {
    "end_ms": 331661,
    "start_ms": 330759,
    "word": "সাফলরাম"
  },
  {
    "end_ms": 332177,
    "start_ms": 331661,
    "word": "গুড়"
  },
  {
    "end_ms": 333079,
    "start_ms": 332177,
    "word": "অকস্মাৎ"
  },
  {
    "end_ms": 334367,
    "start_ms": 333079,
    "word": "ওলাওঠারোগে"
  },
  {
    "end_ms": 335656,
    "start_ms": 334367,
    "word": "প্রাণত্যাগ"
  },
  {
    "end_ms": 336171,
    "start_ms": 335656,
    "word": "করিল"
  },
  {
    "end_ms": 337073,
    "start_ms": 336171,
    "word": "অধ্যায়"
  },
  {
    "end_ms": 337202,
    "start_ms": 337073,
    "word": "2"
  },
  {
    "end_ms": 338233,
    "start_ms": 337202,
    "word": "দ্বিতীয়"
  },
  {
    "end_ms": 339264,
    "start_ms": 338233,
    "word": "পরিচ্ছেদ"
  },
  {
    "end_ms": 339941,
    "start_ms": 339264,
    "word": "যশোদার"
  },
  {
    "end_ms": 340166,
    "start_ms": 339941,
    "word": "আর"
  },
  {
    "end_ms": 340505,
    "start_ms": 340166,
    "word": "দিন"
  },
  {
    "end_ms": 340957,
    "start_ms": 340505,
    "word": "যায়"
  },
  {
    "end_ms": 341182,
    "start_ms": 340957,
    "word": "না"
  },
  {
    "end_ms": 342311,
    "start_ms": 341182,
    "word": "যজমানদিগের"
  },
  {
    "end_ms": 343327,
    "start_ms": 342311,
    "word": "পৌরাহিত্য"
  },
  {
    "end_ms": 343552,
    "start_ms": 343327,
    "word": "কে"
  },
  {
    "end_ms": 343891,
    "start_ms": 343552,
    "word": "করে"
  },
  {
    "end_ms": 345133,
    "start_ms": 343891,
    "word": "কৈবর্ত্তেরা"
  },
  {
    "end_ms": 345358,
    "start_ms": 345133,
    "word": "আর"
  },
  {
    "end_ms": 345584,
    "start_ms": 345358,
    "word": "এক"
  },
  {
    "end_ms": 345810,
    "start_ms": 345584,
    "word": "ঘর"
  },
  {
    "end_ms": 346261,
    "start_ms": 345810,
    "word": "বামন"
  },
  {
    "end_ms": 346713,
    "start_ms": 346261,
    "word": "আনিল"
  },
  {
    "end_ms": 347277,
    "start_ms": 346713,
    "word": "যশোদা"
  },
  {
    "end_ms": 348293,
    "start_ms": 347277,
    "word": "অন্নকষ্টে"
  },
  {
    "end_ms": 348632,
    "start_ms": 348293,
    "word": "ধান"
  },
  {
    "end_ms": 349309,
    "start_ms": 348632,
    "word": "ভানিতে"
  },
  {
    "end_ms": 349873,
    "start_ms": 349309,
    "word": "আরম্ভ"
  },
  {
    "end_ms": 350550,
    "start_ms": 349873,
    "word": "করিলেন"
  },
  {
    "end_ms": 350889,
    "start_ms": 350550,
    "word": "যখন"
  },
  {
    "end_ms": 351905,
    "start_ms": 350889,
    "word": "মুচিরামের"
  },
  {
    "end_ms": 352356,
    "start_ms": 351905,
    "word": "বয়স"
  },
  {
    "end_ms": 352582,
    "start_ms": 352356,
    "word": "দশ"
  },
  {
    "end_ms": 353033,
    "start_ms": 352582,
    "word": "বৎসর"
  },
  {
    "end_ms": 354275,
    "start_ms": 353033,
    "word": "কৈবর্ত্তেরা"
  },
  {
    "end_ms": 354839,
    "start_ms": 354275,
    "word": "চাঁদা"
  },
  {
    "end_ms": 355516,
    "start_ms": 354839,
    "word": "করিয়া"
  },
  {
    "end_ms": 355968,
    "start_ms": 355516,
    "word": "একটা"
  },
  {
    "end_ms": 357097,
    "start_ms": 355968,
    "word": "বারোইয়ারি"
  },
  {
    "end_ms": 357548,
    "start_ms": 357097,
    "word": "পূজা"
  },
  {
    "end_ms": 358000,
    "start_ms": 357548,
    "word": "করিল"
  },
  {
    "end_ms": 358677,
    "start_ms": 358000,
    "word": "যাত্রা"
  },
  {
    "end_ms": 359241,
    "start_ms": 358677,
    "word": "দিবার"
  },
  {
    "end_ms": 359693,
    "start_ms": 359241,
    "word": "জন্য"
  },
  {
    "end_ms": 360821,
    "start_ms": 359693,
    "word": "বারোইয়ারি"
  },
  {
    "end_ms": 362063,
    "start_ms": 360821,
    "word": "কৈবর্ত্তেরা"
  },
  {
    "end_ms": 362627,
    "start_ms": 362063,
    "word": "শস্তা"
  },
  {
    "end_ms": 362966,
    "start_ms": 362627,
    "word": "দরে"
  },
  {
    "end_ms": 363530,
    "start_ms": 362966,
    "word": "হারাণ"
  },
  {
    "end_ms": 364546,
    "start_ms": 363530,
    "word": "অধিকারীকে"
  },
  {
    "end_ms": 364885,
    "start_ms": 364546,
    "word": "তিন"
  },
  {
    "end_ms": 365449,
    "start_ms": 364885,
    "word": "দিনের"
  },
  {
    "end_ms": 365900,
    "start_ms": 365449,
    "word": "জন্য"
  },
  {
    "end_ms": 366578,
    "start_ms": 365900,
    "word": "বায়না"
  },
  {
    "end_ms": 367255,
    "start_ms": 366578,
    "word": "করিয়া"
  },
  {
    "end_ms": 367932,
    "start_ms": 367255,
    "word": "আনিয়া"
  },
  {
    "end_ms": 368835,
    "start_ms": 367932,
    "word": "কলাগাছের"
  },
  {
    "end_ms": 369174,
    "start_ms": 368835,
    "word": "উপর"
  },
  {
    "end_ms": 369512,
    "start_ms": 369174,
    "word": "সরা"
  },
  {
    "end_ms": 370528,
    "start_ms": 369512,
    "word": "জ্বালিয়া"
  },
  {
    "end_ms": 370867,
    "start_ms": 370528,
    "word": "তিন"
  },
  {
    "end_ms": 371544,
    "start_ms": 370867,
    "word": "রাত্রি"
  },
  {
    "end_ms": 372221,
    "start_ms": 371544,
    "word": "যাত্রা"
  },
  {
    "end_ms": 372785,
    "start_ms": 372221,
    "word": "শুনিল"
  },
  {
    "end_ms": 373575,
    "start_ms": 372785,
    "word": "মুচিরাম"
  },
  {
    "end_ms": 373801,
    "start_ms": 373575,
    "word": "এই"
  },
  {
    "end_ms": 374365,
    "start_ms": 373801,
    "word": "প্রথম"
  },
  {
    "end_ms": 375043,
    "start_ms": 374365,
    "word": "যাত্রা"
  },
  {
    "end_ms": 375607,
    "start_ms": 375043,
    "word": "শুনিল"
  },
  {
    "end_ms": 376397,
    "start_ms": 375607,
    "word": "যাত্রার"
  },
  {
    "end_ms": 376736,
    "start_ms": 376397,
    "word": "গান"
  },
  {
    "end_ms": 377526,
    "start_ms": 376736,
    "word": "যাত্রার"
  },
  {
    "end_ms": 377977,
    "start_ms": 377526,
    "word": "গল্প"
  },
  {
    "end_ms": 378429,
    "start_ms": 377977,
    "word": "অনেক"
  },
  {
    "end_ms": 379557,
    "start_ms": 378429,
    "word": "শুনিয়াছিল"
  },
  {
    "end_ms": 380235,
    "start_ms": 379557,
    "word": "কিন্তু"
  },
  {
    "end_ms": 380686,
    "start_ms": 380235,
    "word": "একটা"
  },
  {
    "end_ms": 381138,
    "start_ms": 380686,
    "word": "আস্ত"
  },
  {
    "end_ms": 381815,
    "start_ms": 381138,
    "word": "যাত্রা"
  },
  {
    "end_ms": 382040,
    "start_ms": 381815,
    "word": "এই"
  },
  {
    "end_ms": 382605,
    "start_ms": 382040,
    "word": "প্রথম"
  },
  {
    "end_ms": 383169,
    "start_ms": 382605,
    "word": "শুনিল"
  },
  {
    "end_ms": 383733,
    "start_ms": 383169,
    "word": "চূড়া"
  },
  {
    "end_ms": 384185,
    "start_ms": 383733,
    "word": "ধড়া"
  },
  {
    "end_ms": 384862,
    "start_ms": 384185,
    "word": "ঠেঙ্গা"
  },
  {
    "end_ms": 385314,
    "start_ms": 384862,
    "word": "লাঠি"
  },
  {
    "end_ms": 385765,
    "start_ms": 385314,
    "word": "সহিত"
  },
  {
    "end_ms": 386555,
    "start_ms": 385765,
    "word": "সাক্ষাৎ"
  },
  {
    "end_ms": 387120,
    "start_ms": 386555,
    "word": "কৃষ্ণ"
  },
  {
    "end_ms": 387345,
    "start_ms": 387120,
    "word": "এই"
  },
  {
    "end_ms": 387910,
    "start_ms": 387345,
    "word": "প্রথম"
  },
  {
    "end_ms": 388474,
    "start_ms": 387910,
    "word": "দেখিল"
  },
  {
    "end_ms": 389151,
    "start_ms": 388474,
    "word": "আহ্লাদ"
  },
  {
    "end_ms": 389941,
    "start_ms": 389151,
    "word": "উছলিয়া"
  },
  {
    "end_ms": 390393,
    "start_ms": 389941,
    "word": "উঠিল"
  },
  {
    "end_ms": 391183,
    "start_ms": 390393,
    "word": "নিশ্চিত"
  },
  {
    "end_ms": 391860,
    "start_ms": 391183,
    "word": "সম্বাদ"
  },
  {
    "end_ms": 392311,
    "start_ms": 391860,
    "word": "রাখি"
  },
  {
    "end_ms": 392537,
    "start_ms": 392311,
    "word": "যে"
  },
  {
    "end_ms": 393102,
    "start_ms": 392537,
    "word": "পরদিন"
  },
  {
    "end_ms": 393892,
    "start_ms": 393102,
    "word": "মুচিরাম"
  },
  {
    "end_ms": 394795,
    "start_ms": 393892,
    "word": "গালাগালি"
  },
  {
    "end_ms": 395698,
    "start_ms": 394795,
    "word": "মারামারি"
  },
  {
    "end_ms": 395923,
    "start_ms": 395698,
    "word": "বা"
  },
  {
    "end_ms": 396375,
    "start_ms": 395923,
    "word": "চুরি"
  },
  {
    "end_ms": 396600,
    "start_ms": 396375,
    "word": "বা"
  },
  {
    "end_ms": 397278,
    "start_ms": 396600,
    "word": "মাতাকে"
  },
  {
    "end_ms": 397955,
    "start_ms": 397278,
    "word": "প্রহার"
  },
  {
    "end_ms": 398068,
    "start_ms": 397955,
    "word": "এ"
  },
  {
    "end_ms": 398632,
    "start_ms": 398068,
    "word": "সকলের"
  },
  {
    "end_ms": 399196,
    "start_ms": 398632,
    "word": "কিছুই"
  },
  {
    "end_ms": 399535,
    "start_ms": 399196,
    "word": "করে"
  },
  {
    "end_ms": 399874,
    "start_ms": 399535,
    "word": "নাই"
  },
  {
    "end_ms": 400889,
    "start_ms": 399874,
    "word": "মুচিরামের"
  },
  {
    "end_ms": 401341,
    "start_ms": 400889,
    "word": "একটা"
  },
  {
    "end_ms": 401680,
    "start_ms": 401341,
    "word": "গুণ"
  },
  {
    "end_ms": 402018,
    "start_ms": 401680,
    "word": "ছিল"
  },
  {
    "end_ms": 402808,
    "start_ms": 402018,
    "word": "মুচিরাম"
  },
  {
    "end_ms": 403485,
    "start_ms": 402808,
    "word": "সুকণ্ঠ"
  },
  {
    "end_ms": 404050,
    "start_ms": 403485,
    "word": "প্রথম"
  },
  {
    "end_ms": 404388,
    "start_ms": 404050,
    "word": "দিন"
  },
  {
    "end_ms": 405066,
    "start_ms": 404388,
    "word": "যাত্রা"
  },
  {
    "end_ms": 405856,
    "start_ms": 405066,
    "word": "শুনিয়া"
  },
  {
    "end_ms": 406194,
    "start_ms": 405856,
    "word": "বহু"
  },
  {
    "end_ms": 406759,
    "start_ms": 406194,
    "word": "যত্নে"
  },
  {
    "end_ms": 407210,
    "start_ms": 406759,
    "word": "একটা"
  },
  {
    "end_ms": 407774,
    "start_ms": 407210,
    "word": "গানের"
  },
  {
    "end_ms": 408790,
    "start_ms": 407774,
    "word": "মোহাড়াটা"
  },
  {
    "end_ms": 409919,
    "start_ms": 408790,
    "word": "শিখিয়াছিল"
  },
  {
    "end_ms": 410483,
    "start_ms": 409919,
    "word": "পরদিন"
  },
  {
    "end_ms": 410935,
    "start_ms": 410483,
    "word": "হইতে"
  },
  {
    "end_ms": 411386,
    "start_ms": 410935,
    "word": "মাঠে"
  },
  {
    "end_ms": 411838,
    "start_ms": 411386,
    "word": "মাঠে"
  },
  {
    "end_ms": 412176,
    "start_ms": 411838,
    "word": "সেই"
  },
  {
    "end_ms": 412515,
    "start_ms": 412176,
    "word": "গান"
  },
  {
    "end_ms": 413192,
    "start_ms": 412515,
    "word": "গাইয়া"
  },
  {
    "end_ms": 413869,
    "start_ms": 413192,
    "word": "ফিরিতে"
  },
  {
    "end_ms": 414434,
    "start_ms": 413869,
    "word": "লাগিল"
  },
  {
    "end_ms": 414998,
    "start_ms": 414434,
    "word": "দৈবাৎ"
  },
  {
    "end_ms": 415562,
    "start_ms": 414998,
    "word": "হারাণ"
  },
  {
    "end_ms": 416352,
    "start_ms": 415562,
    "word": "অধিকারী"
  },
  {
    "end_ms": 416804,
    "start_ms": 416352,
    "word": "লোটা"
  },
  {
    "end_ms": 417255,
    "start_ms": 416804,
    "word": "হাতে"
  },
  {
    "end_ms": 418497,
    "start_ms": 417255,
    "word": "পুষ্করিণীতে"
  },
  {
    "end_ms": 420754,
    "start_ms": 418497,
    "word": "হস্তমুখপ্রক্ষালনাদির"
  },
  {
    "end_ms": 421544,
    "start_ms": 420754,
    "word": "অনুরোধে"
  },
  {
    "end_ms": 422673,
    "start_ms": 421544,
    "word": "যাইতেছিলেন"
  },
  {
    "end_ms": 424817,
    "start_ms": 422673,
    "word": "প্রভাতবায়ুপরিচালিত"
  },
  {
    "end_ms": 425382,
    "start_ms": 424817,
    "word": "হইয়া"
  },
  {
    "end_ms": 426398,
    "start_ms": 425382,
    "word": "মুচিরামের"
  },
  {
    "end_ms": 427075,
    "start_ms": 426398,
    "word": "সুস্বর"
  },
  {
    "end_ms": 427865,
    "start_ms": 427075,
    "word": "অধিকারী"
  },
  {
    "end_ms": 428768,
    "start_ms": 427865,
    "word": "মহাশয়ের"
  },
  {
    "end_ms": 429332,
    "start_ms": 428768,
    "word": "কাণের"
  },
  {
    "end_ms": 429784,
    "start_ms": 429332,
    "word": "ভিতর"
  },
  {
    "end_ms": 430122,
    "start_ms": 429784,
    "word": "গেল"
  },
  {
    "end_ms": 430574,
    "start_ms": 430122,
    "word": "কাণে"
  },
  {
    "end_ms": 431138,
    "start_ms": 430574,
    "word": "যাইতে"
  },
  {
    "end_ms": 431702,
    "start_ms": 431138,
    "word": "যাইতে"
  },
  {
    "end_ms": 432154,
    "start_ms": 431702,
    "word": "মনের"
  },
  {
    "end_ms": 432605,
    "start_ms": 432154,
    "word": "ভিতর"
  },
  {
    "end_ms": 432944,
    "start_ms": 432605,
    "word": "গেল"
  },
  {
    "end_ms": 433395,
    "start_ms": 432944,
    "word": "মনের"
  },
  {
    "end_ms": 433847,
    "start_ms": 433395,
    "word": "ভিতর"
  },
  {
    "end_ms": 434411,
    "start_ms": 433847,
    "word": "গিয়া"
  },
  {
    "end_ms": 435201,
    "start_ms": 434411,
    "word": "কল্পনার"
  },
  {
    "end_ms": 436104,
    "start_ms": 435201,
    "word": "সাহায্যে"
  },
  {
    "end_ms": 436669,
    "start_ms": 436104,
    "word": "টাকার"
  },
  {
    "end_ms": 437684,
    "start_ms": 436669,
    "word": "সিন্দুকের"
  },
  {
    "end_ms": 438362,
    "start_ms": 437684,
    "word": "ভিতরেও"
  },
  {
    "end_ms": 439039,
    "start_ms": 438362,
    "word": "প্রবেশ"
  },
  {
    "end_ms": 439490,
    "start_ms": 439039,
    "word": "করিল"
  },
  {
    "end_ms": 440280,
    "start_ms": 439490,
    "word": "অধিকারী"
  },
  {
    "end_ms": 441183,
    "start_ms": 440280,
    "word": "মহাশয়ের"
  },
  {
    "end_ms": 441635,
    "start_ms": 441183,
    "word": "নিকট"
  },
  {
    "end_ms": 442086,
    "start_ms": 441635,
    "word": "গলার"
  },
  {
    "end_ms": 442763,
    "start_ms": 442086,
    "word": "আওয়াজ"
  },
  {
    "end_ms": 443328,
    "start_ms": 442763,
    "word": "টাকার"
  },
  {
    "end_ms": 444118,
    "start_ms": 443328,
    "word": "আওয়াজে"
  },
  {
    "end_ms": 444682,
    "start_ms": 444118,
    "word": "পরিণত"
  },
  {
    "end_ms": 445021,
    "start_ms": 444682,
    "word": "হয়"
  },
  {
    "end_ms": 445247,
    "start_ms": 445021,
    "word": "সে"
  },
  {
    "end_ms": 445698,
    "start_ms": 445247,
    "word": "দোষে"
  },
  {
    "end_ms": 446488,
    "start_ms": 445698,
    "word": "অধিকারী"
  },
  {
    "end_ms": 447165,
    "start_ms": 446488,
    "word": "মহাশয়"
  },
  {
    "end_ms": 447504,
    "start_ms": 447165,
    "word": "একা"
  },
  {
    "end_ms": 447955,
    "start_ms": 447504,
    "word": "দোষী"
  },
  {
    "end_ms": 448407,
    "start_ms": 447955,
    "word": "নহেন"
  },
  {
    "end_ms": 449310,
    "start_ms": 448407,
    "word": "জিজ্ঞাসা"
  },
  {
    "end_ms": 449874,
    "start_ms": 449310,
    "word": "করিলে"
  },
  {
    "end_ms": 450326,
    "start_ms": 449874,
    "word": "অনেক"
  },
  {
    "end_ms": 450777,
    "start_ms": 450326,
    "word": "উকীল"
  },
  {
    "end_ms": 451793,
    "start_ms": 450777,
    "word": "মহাশয়েরা"
  },
  {
    "end_ms": 452244,
    "start_ms": 451793,
    "word": "ইহার"
  },
  {
    "end_ms": 452696,
    "start_ms": 452244,
    "word": "কিছু"
  },
  {
    "end_ms": 453373,
    "start_ms": 452696,
    "word": "নিগূঢ়"
  },
  {
    "end_ms": 454050,
    "start_ms": 453373,
    "word": "তত্ত্ব"
  },
  {
    "end_ms": 454727,
    "start_ms": 454050,
    "word": "বলিয়া"
  },
  {
    "end_ms": 455179,
    "start_ms": 454727,
    "word": "দিতে"
  },
  {
    "end_ms": 455969,
    "start_ms": 455179,
    "word": "পারিবেন"
  },
  {
    "end_ms": 456872,
    "start_ms": 455969,
    "word": "তাঁহাদের"
  },
  {
    "end_ms": 457436,
    "start_ms": 456872,
    "word": "কাছেও"
  },
  {
    "end_ms": 457888,
    "start_ms": 457436,
    "word": "গলার"
  },
  {
    "end_ms": 458565,
    "start_ms": 457888,
    "word": "আওয়াজ"
  },
  {
    "end_ms": 459129,
    "start_ms": 458565,
    "word": "টাকার"
  },
  {
    "end_ms": 459919,
    "start_ms": 459129,
    "word": "আওয়াজে"
  },
  {
    "end_ms": 460484,
    "start_ms": 459919,
    "word": "পরিণত"
  },
  {
    "end_ms": 460822,
    "start_ms": 460484,
    "word": "হয়"
  },
  {
    "end_ms": 462177,
    "start_ms": 460822,
    "word": "উকীলবাবুদেরই"
  },
  {
    "end_ms": 462402,
    "start_ms": 462177,
    "word": "বা"
  },
  {
    "end_ms": 462741,
    "start_ms": 462402,
    "word": "দোষ"
  },
  {
    "end_ms": 462967,
    "start_ms": 462741,
    "word": "কি"
  },
  {
    "end_ms": 463870,
    "start_ms": 462967,
    "word": "Glorious"
  },
  {
    "end_ms": 464660,
    "start_ms": 463870,
    "word": "British"
  },
  {
    "end_ms": 466014,
    "start_ms": 464660,
    "word": "Constitution"
  },
  {
    "end_ms": 466466,
    "start_ms": 466014,
    "word": "হায়"
  },
  {
    "end_ms": 467256,
    "start_ms": 466466,
    "word": "গলাবাজি"
  },
  {
    "end_ms": 467594,
    "start_ms": 467256,
    "word": "সার"
  },
  {
    "end_ms": 468384,
    "start_ms": 467594,
    "word": "অধিকারী"
  },
  {
    "end_ms": 469062,
    "start_ms": 468384,
    "word": "মহাশয়"
  },
  {
    "end_ms": 469852,
    "start_ms": 469062,
    "word": "মানুষের"
  },
  {
    "end_ms": 470416,
    "start_ms": 469852,
    "word": "সঙ্গে"
  },
  {
    "end_ms": 470980,
    "start_ms": 470416,
    "word": "প্রেম"
  },
  {
    "end_ms": 471432,
    "start_ms": 470980,
    "word": "করেন"
  },
  {
    "end_ms": 471658,
    "start_ms": 471432,
    "word": "না"
  },
  {
    "end_ms": 472448,
    "start_ms": 471658,
    "word": "ব্রিটিষ"
  },
  {
    "end_ms": 473915,
    "start_ms": 472448,
    "word": "পার্লিমেণ্টের"
  },
  {
    "end_ms": 474141,
    "start_ms": 473915,
    "word": "মত"
  },
  {
    "end_ms": 474705,
    "start_ms": 474141,
    "word": "এবঞ্চ"
  },
  {
    "end_ms": 476172,
    "start_ms": 474705,
    "word": "কুরঙ্গিণীসদৃশ"
  },
  {
    "end_ms": 477527,
    "start_ms": 476172,
    "word": "মনুষ্যকণ্ঠেই"
  },
  {
    "end_ms": 478091,
    "start_ms": 477527,
    "word": "মুগ্ধ"
  },
  {
    "end_ms": 478543,
    "start_ms": 478091,
    "word": "অতএব"
  },
  {
    "end_ms": 478994,
    "start_ms": 478543,
    "word": "তিনি"
  },
  {
    "end_ms": 479333,
    "start_ms": 478994,
    "word": "হাত"
  },
  {
    "end_ms": 480236,
    "start_ms": 479333,
    "word": "নাড়িয়া"
  },
  {
    "end_ms": 481251,
    "start_ms": 480236,
    "word": "মুচিরামকে"
  },
  {
    "end_ms": 482042,
    "start_ms": 481251,
    "word": "ডাকিলেন"
  },
  {
    "end_ms": 482832,
    "start_ms": 482042,
    "word": "মুচিরাম"
  },
  {
    "end_ms": 483283,
    "start_ms": 482832,
    "word": "আসিল"
  },
  {
    "end_ms": 483847,
    "start_ms": 483283,
    "word": "তাহার"
  },
  {
    "end_ms": 484525,
    "start_ms": 483847,
    "word": "পরিচয়"
  },
  {
    "end_ms": 485428,
    "start_ms": 484525,
    "word": "জিজ্ঞাসা"
  },
  {
    "end_ms": 486105,
    "start_ms": 485428,
    "word": "করিয়া"
  },
  {
    "end_ms": 486782,
    "start_ms": 486105,
    "word": "বলিলেন"
  },
  {
    "end_ms": 487233,
    "start_ms": 486782,
    "word": "তুমি"
  },
  {
    "end_ms": 487685,
    "start_ms": 487233,
    "word": "আমার"
  },
  {
    "end_ms": 488475,
    "start_ms": 487685,
    "word": "যাত্রার"
  },
  {
    "end_ms": 488814,
    "start_ms": 488475,
    "word": "দলে"
  },
  {
    "end_ms": 489491,
    "start_ms": 488814,
    "word": "থাকিবে"
  },
  {
    "end_ms": 490281,
    "start_ms": 489491,
    "word": "মুচিরাম"
  },
  {
    "end_ms": 491071,
    "start_ms": 490281,
    "word": "আহ্লাদে"
  },
  {
    "end_ms": 491748,
    "start_ms": 491071,
    "word": "আটখানা"
  },
  {
    "end_ms": 492200,
    "start_ms": 491748,
    "word": "মাকে"
  },
  {
    "end_ms": 493215,
    "start_ms": 492200,
    "word": "জিজ্ঞাসার"
  },
  {
    "end_ms": 494006,
    "start_ms": 493215,
    "word": "অপেক্ষা"
  },
  {
    "end_ms": 494570,
    "start_ms": 494006,
    "word": "রাখিল"
  },
  {
    "end_ms": 494796,
    "start_ms": 494570,
    "word": "না"
  },
  {
    "end_ms": 495247,
    "start_ms": 494796,
    "word": "তখনই"
  },
  {
    "end_ms": 495811,
    "start_ms": 495247,
    "word": "সঙ্গে"
  },
  {
    "end_ms": 496263,
    "start_ms": 495811,
    "word": "যায়"
  },
  {
    "end_ms": 496940,
    "start_ms": 496263,
    "word": "কিন্তু"
  },
  {
    "end_ms": 497730,
    "start_ms": 496940,
    "word": "অধিকারী"
  },
  {
    "end_ms": 498069,
    "start_ms": 497730,
    "word": "মনে"
  },
  {
    "end_ms": 498520,
    "start_ms": 498069,
    "word": "করিল"
  },
  {
    "end_ms": 498746,
    "start_ms": 498520,
    "word": "যে"
  },
  {
    "end_ms": 499197,
    "start_ms": 498746,
    "word": "পরের"
  },
  {
    "end_ms": 499649,
    "start_ms": 499197,
    "word": "ছেলে"
  },
  {
    "end_ms": 499875,
    "start_ms": 499649,
    "word": "না"
  },
  {
    "end_ms": 500552,
    "start_ms": 499875,
    "word": "বলিয়া"
  },
  {
    "end_ms": 501116,
    "start_ms": 500552,
    "word": "লইয়া"
  },
  {
    "end_ms": 501793,
    "start_ms": 501116,
    "word": "যাওয়া"
  },
  {
    "end_ms": 502245,
    "start_ms": 501793,
    "word": "কিছু"
  },
  {
    "end_ms": 502584,
    "start_ms": 502245,
    "word": "নয়"
  },
  {
    "end_ms": 503044,
    "start_ms": 502584,
    "word": "অতএব"
  },
  {
    "end_ms": 504081,
    "start_ms": 503044,
    "word": "মুচিরামকে"
  },
  {
    "end_ms": 504657,
    "start_ms": 504081,
    "word": "সঙ্গে"
  },
  {
    "end_ms": 505348,
    "start_ms": 504657,
    "word": "করিয়া"
  },
  {
    "end_ms": 505924,
    "start_ms": 505348,
    "word": "তাহার"
  },
  {
    "end_ms": 506269,
    "start_ms": 505924,
    "word": "মার"
  },
  {
    "end_ms": 506730,
    "start_ms": 506269,
    "word": "নিকট"
  },
  {
    "end_ms": 507075,
    "start_ms": 506730,
    "word": "গেল"
  },
  {
    "end_ms": 507882,
    "start_ms": 507075,
    "word": "শুনিয়া"
  },
  {
    "end_ms": 508457,
    "start_ms": 507882,
    "word": "যশোদা"
  },
  {
    "end_ms": 508803,
    "start_ms": 508457,
    "word": "বড়"
  },
  {
    "end_ms": 509379,
    "start_ms": 508803,
    "word": "কাঁদা"
  },
  {
    "end_ms": 509840,
    "start_ms": 509379,
    "word": "কাটা"
  },
  {
    "end_ms": 510415,
    "start_ms": 509840,
    "word": "আরম্ভ"
  },
  {
    "end_ms": 510876,
    "start_ms": 510415,
    "word": "করিল"
  },
  {
    "end_ms": 511222,
    "start_ms": 510876,
    "word": "সবে"
  },
  {
    "end_ms": 511682,
    "start_ms": 511222,
    "word": "একটি"
  },
  {
    "end_ms": 512143,
    "start_ms": 511682,
    "word": "ছেলে"
  },
  {
    "end_ms": 512373,
    "start_ms": 512143,
    "word": "আর"
  },
  {
    "end_ms": 512719,
    "start_ms": 512373,
    "word": "কেহ"
  },
  {
    "end_ms": 513065,
    "start_ms": 512719,
    "word": "নাই"
  },
  {
    "end_ms": 513295,
    "start_ms": 513065,
    "word": "কি"
  },
  {
    "end_ms": 514101,
    "start_ms": 513295,
    "word": "প্রকারে"
  },
  {
    "end_ms": 515022,
    "start_ms": 514101,
    "word": "ছাড়িয়া"
  },
  {
    "end_ms": 515483,
    "start_ms": 515022,
    "word": "দিবে"
  },
  {
    "end_ms": 516059,
    "start_ms": 515483,
    "word": "এদিকে"
  },
  {
    "end_ms": 516520,
    "start_ms": 516059,
    "word": "আবার"
  },
  {
    "end_ms": 516980,
    "start_ms": 516520,
    "word": "অন্ন"
  },
  {
    "end_ms": 517441,
    "start_ms": 516980,
    "word": "জুটে"
  },
  {
    "end_ms": 517672,
    "start_ms": 517441,
    "word": "না"
  },
  {
    "end_ms": 518017,
    "start_ms": 517672,
    "word": "যদি"
  },
  {
    "end_ms": 518478,
    "start_ms": 518017,
    "word": "একটা"
  },
  {
    "end_ms": 519054,
    "start_ms": 518478,
    "word": "খাবার"
  },
  {
    "end_ms": 519630,
    "start_ms": 519054,
    "word": "উপায়"
  },
  {
    "end_ms": 520321,
    "start_ms": 519630,
    "word": "হইতেছে"
  },
  {
    "end_ms": 520781,
    "start_ms": 520321,
    "word": "কেমন"
  },
  {
    "end_ms": 521588,
    "start_ms": 520781,
    "word": "করিয়াই"
  },
  {
    "end_ms": 521818,
    "start_ms": 521588,
    "word": "বা"
  },
  {
    "end_ms": 522048,
    "start_ms": 521818,
    "word": "না"
  },
  {
    "end_ms": 522394,
    "start_ms": 522048,
    "word": "বলে"
  },
  {
    "end_ms": 523085,
    "start_ms": 522394,
    "word": "বিধাতা"
  },
  {
    "end_ms": 523315,
    "start_ms": 523085,
    "word": "কি"
  },
  {
    "end_ms": 523546,
    "start_ms": 523315,
    "word": "আর"
  },
  {
    "end_ms": 523891,
    "start_ms": 523546,
    "word": "এমন"
  },
  {
    "end_ms": 524467,
    "start_ms": 523891,
    "word": "সুযোগ"
  },
  {
    "end_ms": 525158,
    "start_ms": 524467,
    "word": "করিয়া"
  },
  {
    "end_ms": 525734,
    "start_ms": 525158,
    "word": "দিবেন"
  },
  {
    "end_ms": 526079,
    "start_ms": 525734,
    "word": "আমি"
  },
  {
    "end_ms": 526310,
    "start_ms": 526079,
    "word": "না"
  },
  {
    "end_ms": 527001,
    "start_ms": 526310,
    "word": "দেখিতে"
  },
  {
    "end_ms": 527346,
    "start_ms": 527001,
    "word": "পাই"
  },
  {
    "end_ms": 527692,
    "start_ms": 527346,
    "word": "তবু"
  },
  {
    "end_ms": 527807,
    "start_ms": 527692,
    "word": "ত"
  },
  {
    "end_ms": 528613,
    "start_ms": 527807,
    "word": "মুচিরাম"
  },
  {
    "end_ms": 528959,
    "start_ms": 528613,
    "word": "ভাল"
  },
  {
    "end_ms": 529535,
    "start_ms": 528959,
    "word": "খাইবে"
  },
  {
    "end_ms": 529880,
    "start_ms": 529535,
    "word": "ভাল"
  },
  {
    "end_ms": 530571,
    "start_ms": 529880,
    "word": "থাকিবে"
  },
  {
    "end_ms": 530917,
    "start_ms": 530571,
    "word": "ভাল"
  },
  {
    "end_ms": 531493,
    "start_ms": 530917,
    "word": "পরিবে"
  },
  {
    "end_ms": 532069,
    "start_ms": 531493,
    "word": "যশোদা"
  },
  {
    "end_ms": 533566,
    "start_ms": 532069,
    "word": "যাত্রাওয়ালার"
  },
  {
    "end_ms": 534027,
    "start_ms": 533566,
    "word": "দুঃখ"
  },
  {
    "end_ms": 534602,
    "start_ms": 534027,
    "word": "জানিত"
  },
  {
    "end_ms": 534833,
    "start_ms": 534602,
    "word": "না"
  },
  {
    "end_ms": 535524,
    "start_ms": 534833,
    "word": "অগত্যা"
  },
  {
    "end_ms": 535985,
    "start_ms": 535524,
    "word": "পাঁচ"
  },
  {
    "end_ms": 536445,
    "start_ms": 535985,
    "word": "টাকা"
  },
  {
    "end_ms": 537021,
    "start_ms": 536445,
    "word": "মাসিক"
  },
  {
    "end_ms": 537482,
    "start_ms": 537021,
    "word": "বেতন"
  },
  {
    "end_ms": 537827,
    "start_ms": 537482,
    "word": "রফা"
  },
  {
    "end_ms": 538518,
    "start_ms": 537827,
    "word": "করিয়া"
  },
  {
    "end_ms": 539094,
    "start_ms": 538518,
    "word": "যশোদা"
  },
  {
    "end_ms": 540131,
    "start_ms": 539094,
    "word": "মুচিরামকে"
  },
  {
    "end_ms": 540707,
    "start_ms": 540131,
    "word": "হারাণ"
  },
  {
    "end_ms": 541628,
    "start_ms": 540707,
    "word": "অধিকারীর"
  },
  {
    "end_ms": 542204,
    "start_ms": 541628,
    "word": "হস্তে"
  },
  {
    "end_ms": 542895,
    "start_ms": 542204,
    "word": "সমর্পণ"
  },
  {
    "end_ms": 543356,
    "start_ms": 542895,
    "word": "করিল"
  },
  {
    "end_ms": 543701,
    "start_ms": 543356,
    "word": "তার"
  },
  {
    "end_ms": 543932,
    "start_ms": 543701,
    "word": "পর"
  },
  {
    "end_ms": 544968,
    "start_ms": 543932,
    "word": "আছাড়িয়া"
  },
  {
    "end_ms": 545774,
    "start_ms": 544968,
    "word": "পড়িয়া"
  },
  {
    "end_ms": 546581,
    "start_ms": 545774,
    "word": "স্বামীর"
  },
  {
    "end_ms": 547041,
    "start_ms": 546581,
    "word": "জন্য"
  },
  {
    "end_ms": 547848,
    "start_ms": 547041,
    "word": "কাঁদিতে"
  },
  {
    "end_ms": 548424,
    "start_ms": 547848,
    "word": "লাগিল"
  }
]
