{
  "candidate_count": 47,
  "candidate_slugs": [
    "bn-027",
    "bn-031",
    "bn-035",
    "bn-036",
    "bn-041",
    "bn-059",
    "bn-060",
    "bn-066",
    "book-0986aeb7e3",
    "book-0deb35c750",
    "book-0fbdaa730e",
    "book-1090573dff",
    "book-2b9853ec52",
    "book-2ddbed8293",
    "book-2e468c4990",
    "book-4968248842",
    "book-4b944e64fa",
    "book-5461971092",
    "book-5704b31005",
    "book-5aedda79fe",
    "book-63afd5e9be",
    "book-754da4eab8",
    "book-827fdc7aee",
    "book-88ded9b47c",
    "book-95624627d5",
    "book-9a7f771921",
    "book-a23625bf36",
    "book-a4a369483f",
    "book-a74c1a1451",
    "book-ac5a71075e",
    "book-b9d47814a8",
    "book-bfc51280b3",
    "book-c307a57868",
    "book-c7f3ce526c",
    "book-c85323409f",
    "book-d19e96859f",
    "book-d2fe532e1c",
    "book-edfcf810c5",
    "book-ef193ffc52",
    "book-f5d593e1f4",
    "book-fbdf2991ab",
    "lokrahasya",
    "mrinalini",
    "muchiram-gurer-jibanchorit",
    "nishkriti",
    "radharani",
    "yugalanguriya"
  ],
  "candidates": [
    {
      "accessibility_qa_required": true,
      "audio_file_count": 1,
      "author": "রবীন্দ্রনাথ ঠাকুর",
      "automatic_improvement_count": 0,
      "candidate_dir": "internal/audiobook_lab/bengali_store_candidates/bn-027",
      "candidate_slug": "bn-027",
      "human_qa_required": true,
      "missing_required_files": [],
      "objective_audio_score": 8.8,
      "objective_audio_status": "PASS",
      "public_serving_status": "BLOCKED",
      "release_status": "HOLD_BENGALI_AUDIOBOOK_QA_REQUIRED",
      "rights_review_required": true,
      "sidecar_file_count": 3,
      "sync_usability_score": 5.8,
      "title": "অপরিচিতা"
    },
    {
      "accessibility_qa_required": true,
      "audio_file_count": 1,
      "author": "শরৎচন্দ্র চট্টোপাধ্যায়",
      "automatic_improvement_count": 0,
      "candidate_dir": "internal/audiobook_lab/bengali_store_candidates/bn-031",
      "candidate_slug": "bn-031",
      "human_qa_required": true,
      "missing_required_files": [],
      "objective_audio_score": 8.8,
      "objective_audio_status": "PASS",
      "public_serving_status": "BLOCKED",
      "release_status": "HOLD_BENGALI_AUDIOBOOK_QA_REQUIRED",
      "rights_review_required": true,
      "sidecar_file_count": 3,
      "sync_usability_score": 4.0,
      "title": "মহেশ"
    },
    {
      "accessibility_qa_required": true,
      "audio_file_count": 1,
      "author": "শরৎচন্দ্র চট্টোপাধ্যায়",
      "automatic_improvement_count": 0,
      "candidate_dir": "internal/audiobook_lab/bengali_store_candidates/bn-035",
      "candidate_slug": "bn-035",
      "human_qa_required": true,
      "missing_required_files": [],
      "objective_audio_score": 8.8,
      "objective_audio_status": "PASS",
      "public_serving_status": "BLOCKED",
      "release_status": "HOLD_BENGALI_AUDIOBOOK_QA_REQUIRED",
      "rights_review_required": true,
      "sidecar_file_count": 3,
      "sync_usability_score": 4.0,
      "title": "বড়দিদি"
    },
    {
      "accessibility_qa_required": true,
      "audio_file_count": 1,
      "author": "শরৎচন্দ্র চট্টোপাধ্যায়",
      "automatic_improvement_count": 0,
      "candidate_dir": "internal/audiobook_lab/bengali_store_candidates/bn-036",
      "candidate_slug": "bn-036",
      "human_qa_required": true,
      "missing_required_files": [],
      "objective_audio_score": 8.8,
      "objective_audio_status": "PASS",
      "public_serving_status": "BLOCKED",
      "release_status": "HOLD_BENGALI_AUDIOBOOK_QA_REQUIRED",
      "rights_review_required": true,
      "sidecar_file_count": 3,
      "sync_usability_score": 4.0,
      "title": "মেজদিদি"
    },
    {
      "accessibility_qa_required": true,
      "audio_file_count": 1,
      "author": "শরৎচন্দ্র চট্টোপাধ্যায়",
      "automatic_improvement_count": 0,
      "candidate_dir": "internal/audiobook_lab/bengali_store_candidates/bn-041",
      "candidate_slug": "bn-041",
      "human_qa_required": true,
      "missing_required_files": [],
      "objective_audio_score": 8.8,
      "objective_audio_status": "PASS",
      "public_serving_status": "BLOCKED",
      "release_status": "HOLD_BENGALI_AUDIOBOOK_QA_REQUIRED",
      "rights_review_required": true,
      "sidecar_file_count": 3,
      "sync_usability_score": 4.0,
      "title": "আঁধারে আলো"
    },
    {
      "accessibility_qa_required": true,
      "audio_file_count": 1,
      "author": "বঙ্কিমচন্দ্র চট্টোপাধ্যায়",
      "automatic_improvement_count": 0,
      "candidate_dir": "internal/audiobook_lab/bengali_store_candidates/bn-059",
      "candidate_slug": "bn-059",
      "human_qa_required": true,
      "missing_required_files": [],
      "objective_audio_score": 8.8,
      "objective_audio_status": "PASS",
      "public_serving_status": "BLOCKED",
      "release_status": "HOLD_BENGALI_AUDIOBOOK_QA_REQUIRED",
      "rights_review_required": true,
      "sidecar_file_count": 3,
      "sync_usability_score": 4.0,
      "title": "কমলাকান্তের দপ্তর"
    },
    {
      "accessibility_qa_required": true,
      "audio_file_count": 1,
      "author": "বঙ্কিমচন্দ্র চট্টোপাধ্যায়",
      "automatic_improvement_count": 0,
      "candidate_dir": "internal/audiobook_lab/bengali_store_candidates/bn-060",
      "candidate_slug": "bn-060",
      "human_qa_required": true,
      "missing_required_files": [],
      "objective_audio_score": 8.8,
      "objective_audio_status": "PASS",
      "public_serving_status": "BLOCKED",
      "release_status": "HOLD_BENGALI_AUDIOBOOK_QA_REQUIRED",
      "rights_review_required": true,
      "sidecar_file_count": 3,
      "sync_usability_score": 4.0,
      "title": "ইন্দিরা"
    },
    {
      "accessibility_qa_required": true,
      "audio_file_count": 1,
      "author": "বঙ্কিমচন্দ্র চট্টোপাধ্যায়",
      "automatic_improvement_count": 0,
      "candidate_dir": "internal/audiobook_lab/bengali_store_candidates/bn-066",
      "candidate_slug": "bn-066",
      "human_qa_required": true,
      "missing_required_files": [],
      "objective_audio_score": 8.8,
      "objective_audio_status": "PASS",
      "public_serving_status": "BLOCKED",
      "release_status": "HOLD_BENGALI_AUDIOBOOK_QA_REQUIRED",
      "rights_review_required": true,
      "sidecar_file_count": 3,
      "sync_usability_score": 4.0,
      "title": "আনন্দমঠ"
    },
    {
      "accessibility_qa_required": true,
      "audio_file_count": 1,
      "author": "রবীন্দ্রনাথ ঠাকুর",
      "automatic_improvement_count": 0,
      "candidate_dir": "internal/audiobook_lab/bengali_store_candidates/book-0986aeb7e3",
      "candidate_slug": "book-0986aeb7e3",
      "human_qa_required": true,
      "missing_required_files": [],
      "objective_audio_score": 8.8,
      "objective_audio_status": "PASS",
      "public_serving_status": "BLOCKED",
      "release_status": "HOLD_BENGALI_AUDIOBOOK_QA_REQUIRED",
      "rights_review_required": true,
      "sidecar_file_count": 3,
      "sync_usability_score": 7.6,
      "title": "হৈমন্তী"
    },
    {
      "accessibility_qa_required": true,
      "audio_file_count": 1,
      "author": "রবীন্দ্রনাথ ঠাকুর",
      "automatic_improvement_count": 0,
      "candidate_dir": "internal/audiobook_lab/bengali_store_candidates/book-0deb35c750",
      "candidate_slug": "book-0deb35c750",
      "human_qa_required": true,
      "missing_required_files": [],
      "objective_audio_score": 8.8,
      "objective_audio_status": "PASS",
      "public_serving_status": "BLOCKED",
      "release_status": "HOLD_BENGALI_AUDIOBOOK_QA_REQUIRED",
      "rights_review_required": true,
      "sidecar_file_count": 3,
      "sync_usability_score": 8.0,
      "title": "খাতা"
    },
    {
      "accessibility_qa_required": true,
      "audio_file_count": 1,
      "author": "রবীন্দ্রনাথ ঠাকুর",
      "automatic_improvement_count": 0,
      "candidate_dir": "internal/audiobook_lab/bengali_store_candidates/book-0fbdaa730e",
      "candidate_slug": "book-0fbdaa730e",
      "human_qa_required": true,
      "missing_required_files": [],
      "objective_audio_score": 8.8,
      "objective_audio_status": "PASS",
      "public_serving_status": "BLOCKED",
      "release_status": "HOLD_BENGALI_AUDIOBOOK_QA_REQUIRED",
      "rights_review_required": true,
      "sidecar_file_count": 3,
      "sync_usability_score": 4.0,
      "title": "গুপ্তধন"
    },
    {
      "accessibility_qa_required": true,
      "audio_file_count": 1,
      "author": "রবীন্দ্রনাথ ঠাকুর",
      "automatic_improvement_count": 0,
      "candidate_dir": "internal/audiobook_lab/bengali_store_candidates/book-1090573dff",
      "candidate_slug": "book-1090573dff",
      "human_qa_required": true,
      "missing_required_files": [],
      "objective_audio_score": 8.8,
      "objective_audio_status": "PASS",
      "public_serving_status": "BLOCKED",
      "release_status": "HOLD_BENGALI_AUDIOBOOK_QA_REQUIRED",
      "rights_review_required": true,
      "sidecar_file_count": 3,
      "sync_usability_score": 7.6,
      "title": "ছুটি"
    },
    {
      "accessibility_qa_required": true,
      "audio_file_count": 1,
      "author": "রবীন্দ্রনাথ ঠাকুর",
      "automatic_improvement_count": 0,
      "candidate_dir": "internal/audiobook_lab/bengali_store_candidates/book-2b9853ec52",
      "candidate_slug": "book-2b9853ec52",
      "human_qa_required": true,
      "missing_required_files": [],
      "objective_audio_score": 8.8,
      "objective_audio_status": "PASS",
      "public_serving_status": "BLOCKED",
      "release_status": "HOLD_BENGALI_AUDIOBOOK_QA_REQUIRED",
      "rights_review_required": true,
      "sidecar_file_count": 3,
      "sync_usability_score": 7.0,
      "title": "দুই বিঘা জমি"
    },
    {
      "accessibility_qa_required": true,
      "audio_file_count": 1,
      "author": "রবীন্দ্রনাথ ঠাকুর",
      "automatic_improvement_count": 0,
      "candidate_dir": "internal/audiobook_lab/bengali_store_candidates/book-2ddbed8293",
      "candidate_slug": "book-2ddbed8293",
      "human_qa_required": true,
      "missing_required_files": [],
      "objective_audio_score": 8.8,
      "objective_audio_status": "PASS",
      "public_serving_status": "BLOCKED",
      "release_status": "HOLD_BENGALI_AUDIOBOOK_QA_REQUIRED",
      "rights_review_required": true,
      "sidecar_file_count": 3,
      "sync_usability_score": 7.6,
      "title": "ব্যবধান"
    },
    {
      "accessibility_qa_required": true,
      "audio_file_count": 1,
      "author": "রবীন্দ্রনাথ ঠাকুর",
      "automatic_improvement_count": 0,
      "candidate_dir": "internal/audiobook_lab/bengali_store_candidates/book-2e468c4990",
      "candidate_slug": "book-2e468c4990",
      "human_qa_required": true,
      "missing_required_files": [],
      "objective_audio_score": 8.8,
      "objective_audio_status": "PASS",
      "public_serving_status": "BLOCKED",
      "release_status": "HOLD_BENGALI_AUDIOBOOK_QA_REQUIRED",
      "rights_review_required": true,
      "sidecar_file_count": 3,
      "sync_usability_score": 8.0,
      "title": "কাবুলিওয়ালা"
    },
    {
      "accessibility_qa_required": true,
      "audio_file_count": 1,
      "author": "রবীন্দ্রনাথ ঠাকুর",
      "automatic_improvement_count": 0,
      "candidate_dir": "internal/audiobook_lab/bengali_store_candidates/book-4968248842",
      "candidate_slug": "book-4968248842",
      "human_qa_required": true,
      "missing_required_files": [],
      "objective_audio_score": 8.8,
      "objective_audio_status": "PASS",
      "public_serving_status": "BLOCKED",
      "release_status": "HOLD_BENGALI_AUDIOBOOK_QA_REQUIRED",
      "rights_review_required": true,
      "sidecar_file_count": 3,
      "sync_usability_score": 7.0,
      "title": "বলাই"
    },
    {
      "accessibility_qa_required": true,
      "audio_file_count": 1,
      "author": "রবীন্দ্রনাথ ঠাকুর",
      "automatic_improvement_count": 0,
      "candidate_dir": "internal/audiobook_lab/bengali_store_candidates/book-4b944e64fa",
      "candidate_slug": "book-4b944e64fa",
      "human_qa_required": true,
      "missing_required_files": [],
      "objective_audio_score": 8.8,
      "objective_audio_status": "PASS",
      "public_serving_status": "BLOCKED",
      "release_status": "HOLD_BENGALI_AUDIOBOOK_QA_REQUIRED",
      "rights_review_required": true,
      "sidecar_file_count": 3,
      "sync_usability_score": 7.6,
      "title": "একরাত্রি"
    },
    {
      "accessibility_qa_required": true,
      "audio_file_count": 1,
      "author": "রবীন্দ্রনাথ ঠাকুর",
      "automatic_improvement_count": 0,
      "candidate_dir": "internal/audiobook_lab/bengali_store_candidates/book-5461971092",
      "candidate_slug": "book-5461971092",
      "human_qa_required": true,
      "missing_required_files": [],
      "objective_audio_score": 8.8,
      "objective_audio_status": "PASS",
      "public_serving_status": "BLOCKED",
      "release_status": "HOLD_BENGALI_AUDIOBOOK_QA_REQUIRED",
      "rights_review_required": true,
      "sidecar_file_count": 3,
      "sync_usability_score": 7.6,
      "title": "মেঘ ও রৌদ্র"
    },
    {
      "accessibility_qa_required": true,
      "audio_file_count": 1,
      "author": "রবীন্দ্রনাথ ঠাকুর",
      "automatic_improvement_count": 0,
      "candidate_dir": "internal/audiobook_lab/bengali_store_candidates/book-5704b31005",
      "candidate_slug": "book-5704b31005",
      "human_qa_required": true,
      "missing_required_files": [],
      "objective_audio_score": 8.8,
      "objective_audio_status": "PASS",
      "public_serving_status": "BLOCKED",
      "release_status": "HOLD_BENGALI_AUDIOBOOK_QA_REQUIRED",
      "rights_review_required": true,
      "sidecar_file_count": 3,
      "sync_usability_score": 8.0,
      "title": "বিচারক"
    },
    {
      "accessibility_qa_required": true,
      "audio_file_count": 1,
      "author": "রবীন্দ্রনাথ ঠাকুর",
      "automatic_improvement_count": 0,
      "candidate_dir": "internal/audiobook_lab/bengali_store_candidates/book-5aedda79fe",
      "candidate_slug": "book-5aedda79fe",
      "human_qa_required": true,
      "missing_required_files": [],
      "objective_audio_score": 8.8,
      "objective_audio_status": "PASS",
      "public_serving_status": "BLOCKED",
      "release_status": "HOLD_BENGALI_AUDIOBOOK_QA_REQUIRED",
      "rights_review_required": true,
      "sidecar_file_count": 3,
      "sync_usability_score": 7.6,
      "title": "শাস্তি"
    },
    {
      "accessibility_qa_required": true,
      "audio_file_count": 1,
      "author": "রবীন্দ্রনাথ ঠাকুর",
      "automatic_improvement_count": 0,
      "candidate_dir": "internal/audiobook_lab/bengali_store_candidates/book-63afd5e9be",
      "candidate_slug": "book-63afd5e9be",
      "human_qa_required": true,
      "missing_required_files": [],
      "objective_audio_score": 8.8,
      "objective_audio_status": "PASS",
      "public_serving_status": "BLOCKED",
      "release_status": "HOLD_BENGALI_AUDIOBOOK_QA_REQUIRED",
      "rights_review_required": true,
      "sidecar_file_count": 3,
      "sync_usability_score": 7.6,
      "title": "দেনাপাওনা"
    },
    {
      "accessibility_qa_required": true,
      "audio_file_count": 1,
      "author": "রবীন্দ্রনাথ ঠাকুর",
      "automatic_improvement_count": 0,
      "candidate_dir": "internal/audiobook_lab/bengali_store_candidates/book-754da4eab8",
      "candidate_slug": "book-754da4eab8",
      "human_qa_required": true,
      "missing_required_files": [],
      "objective_audio_score": 8.8,
      "objective_audio_status": "PASS",
      "public_serving_status": "BLOCKED",
      "release_status": "HOLD_BENGALI_AUDIOBOOK_QA_REQUIRED",
      "rights_review_required": true,
      "sidecar_file_count": 3,
      "sync_usability_score": 7.6,
      "title": "তারাপ্রসন্নের কীর্তি"
    },
    {
      "accessibility_qa_required": true,
      "audio_file_count": 1,
      "author": "রবীন্দ্রনাথ ঠাকুর",
      "automatic_improvement_count": 0,
      "candidate_dir": "internal/audiobook_lab/bengali_store_candidates/book-827fdc7aee",
      "candidate_slug": "book-827fdc7aee",
      "human_qa_required": true,
      "missing_required_files": [],
      "objective_audio_score": 8.8,
      "objective_audio_status": "PASS",
      "public_serving_status": "BLOCKED",
      "release_status": "HOLD_BENGALI_AUDIOBOOK_QA_REQUIRED",
      "rights_review_required": true,
      "sidecar_file_count": 3,
      "sync_usability_score": 5.2,
      "title": "রাসমণির ছেলে"
    },
    {
      "accessibility_qa_required": true,
      "audio_file_count": 1,
      "author": "রবীন্দ্রনাথ ঠাকুর",
      "automatic_improvement_count": 0,
      "candidate_dir": "internal/audiobook_lab/bengali_store_candidates/book-88ded9b47c",
      "candidate_slug": "book-88ded9b47c",
      "human_qa_required": true,
      "missing_required_files": [],
      "objective_audio_score": 8.8,
      "objective_audio_status": "PASS",
      "public_serving_status": "BLOCKED",
      "release_status": "HOLD_BENGALI_AUDIOBOOK_QA_REQUIRED",
      "rights_review_required": true,
      "sidecar_file_count": 3,
      "sync_usability_score": 8.0,
      "title": "মানভঞ্জন"
    },
    {
      "accessibility_qa_required": true,
      "audio_file_count": 1,
      "author": "রবীন্দ্রনাথ ঠাকুর",
      "automatic_improvement_count": 0,
      "candidate_dir": "internal/audiobook_lab/bengali_store_candidates/book-95624627d5",
      "candidate_slug": "book-95624627d5",
      "human_qa_required": true,
      "missing_required_files": [],
      "objective_audio_score": 8.8,
      "objective_audio_status": "PASS",
      "public_serving_status": "BLOCKED",
      "release_status": "HOLD_BENGALI_AUDIOBOOK_QA_REQUIRED",
      "rights_review_required": true,
      "sidecar_file_count": 3,
      "sync_usability_score": 7.6,
      "title": "মধ্যবর্তিনী"
    },
    {
      "accessibility_qa_required": true,
      "audio_file_count": 1,
      "author": "রবীন্দ্রনাথ ঠাকুর",
      "automatic_improvement_count": 0,
      "candidate_dir": "internal/audiobook_lab/bengali_store_candidates/book-9a7f771921",
      "candidate_slug": "book-9a7f771921",
      "human_qa_required": true,
      "missing_required_files": [],
      "objective_audio_score": 8.8,
      "objective_audio_status": "PASS",
      "public_serving_status": "BLOCKED",
      "release_status": "HOLD_BENGALI_AUDIOBOOK_QA_REQUIRED",
      "rights_review_required": true,
      "sidecar_file_count": 3,
      "sync_usability_score": 7.6,
      "title": "কর্মফল"
    },
    {
      "accessibility_qa_required": true,
      "audio_file_count": 1,
      "author": "রবীন্দ্রনাথ ঠাকুর",
      "automatic_improvement_count": 0,
      "candidate_dir": "internal/audiobook_lab/bengali_store_candidates/book-a23625bf36",
      "candidate_slug": "book-a23625bf36",
      "human_qa_required": true,
      "missing_required_files": [],
      "objective_audio_score": 8.8,
      "objective_audio_status": "PASS",
      "public_serving_status": "BLOCKED",
      "release_status": "HOLD_BENGALI_AUDIOBOOK_QA_REQUIRED",
      "rights_review_required": true,
      "sidecar_file_count": 3,
      "sync_usability_score": 7.6,
      "title": "সমাপ্তি"
    },
    {
      "accessibility_qa_required": true,
      "audio_file_count": 1,
      "author": "রবীন্দ্রনাথ ঠাকুর",
      "automatic_improvement_count": 0,
      "candidate_dir": "internal/audiobook_lab/bengali_store_candidates/book-a4a369483f",
      "candidate_slug": "book-a4a369483f",
      "human_qa_required": true,
      "missing_required_files": [],
      "objective_audio_score": 8.8,
      "objective_audio_status": "PASS",
      "public_serving_status": "BLOCKED",
      "release_status": "HOLD_BENGALI_AUDIOBOOK_QA_REQUIRED",
      "rights_review_required": true,
      "sidecar_file_count": 3,
      "sync_usability_score": 7.6,
      "title": "সম্পত্তি সমর্পণ"
    },
    {
      "accessibility_qa_required": true,
      "audio_file_count": 1,
      "author": "রবীন্দ্রনাথ ঠাকুর",
      "automatic_improvement_count": 0,
      "candidate_dir": "internal/audiobook_lab/bengali_store_candidates/book-a74c1a1451",
      "candidate_slug": "book-a74c1a1451",
      "human_qa_required": true,
      "missing_required_files": [],
      "objective_audio_score": 8.8,
      "objective_audio_status": "PASS",
      "public_serving_status": "BLOCKED",
      "release_status": "HOLD_BENGALI_AUDIOBOOK_QA_REQUIRED",
      "rights_review_required": true,
      "sidecar_file_count": 3,
      "sync_usability_score": 7.6,
      "title": "দালিয়া"
    },
    {
      "accessibility_qa_required": true,
      "audio_file_count": 1,
      "author": "রবীন্দ্রনাথ ঠাকুর",
      "automatic_improvement_count": 0,
      "candidate_dir": "internal/audiobook_lab/bengali_store_candidates/book-ac5a71075e",
      "candidate_slug": "book-ac5a71075e",
      "human_qa_required": true,
      "missing_required_files": [],
      "objective_audio_score": 8.8,
      "objective_audio_status": "PASS",
      "public_serving_status": "BLOCKED",
      "release_status": "HOLD_BENGALI_AUDIOBOOK_QA_REQUIRED",
      "rights_review_required": true,
      "sidecar_file_count": 3,
      "sync_usability_score": 7.6,
      "title": "পোস্টমাস্টার"
    },
    {
      "accessibility_qa_required": true,
      "audio_file_count": 1,
      "author": "রবীন্দ্রনাথ ঠাকুর",
      "automatic_improvement_count": 0,
      "candidate_dir": "internal/audiobook_lab/bengali_store_candidates/book-b9d47814a8",
      "candidate_slug": "book-b9d47814a8",
      "human_qa_required": true,
      "missing_required_files": [],
      "objective_audio_score": 8.8,
      "objective_audio_status": "PASS",
      "public_serving_status": "BLOCKED",
      "release_status": "HOLD_BENGALI_AUDIOBOOK_QA_REQUIRED",
      "rights_review_required": true,
      "sidecar_file_count": 3,
      "sync_usability_score": 8.0,
      "title": "নিশীথে"
    },
    {
      "accessibility_qa_required": true,
      "audio_file_count": 1,
      "author": "রবীন্দ্রনাথ ঠাকুর",
      "automatic_improvement_count": 0,
      "candidate_dir": "internal/audiobook_lab/bengali_store_candidates/book-bfc51280b3",
      "candidate_slug": "book-bfc51280b3",
      "human_qa_required": true,
      "missing_required_files": [],
      "objective_audio_score": 8.8,
      "objective_audio_status": "PASS",
      "public_serving_status": "BLOCKED",
      "release_status": "HOLD_BENGALI_AUDIOBOOK_QA_REQUIRED",
      "rights_review_required": true,
      "sidecar_file_count": 3,
      "sync_usability_score": 8.0,
      "title": "অতিথি"
    },
    {
      "accessibility_qa_required": true,
      "audio_file_count": 1,
      "author": "রবীন্দ্রনাথ ঠাকুর",
      "automatic_improvement_count": 0,
      "candidate_dir": "internal/audiobook_lab/bengali_store_candidates/book-c307a57868",
      "candidate_slug": "book-c307a57868",
      "human_qa_required": true,
      "missing_required_files": [],
      "objective_audio_score": 8.8,
      "objective_audio_status": "PASS",
      "public_serving_status": "BLOCKED",
      "release_status": "HOLD_BENGALI_AUDIOBOOK_QA_REQUIRED",
      "rights_review_required": true,
      "sidecar_file_count": 3,
      "sync_usability_score": 7.6,
      "title": "স্ত্রীর পত্র"
    },
    {
      "accessibility_qa_required": true,
      "audio_file_count": 1,
      "author": "রবীন্দ্রনাথ ঠাকুর",
      "automatic_improvement_count": 0,
      "candidate_dir": "internal/audiobook_lab/bengali_store_candidates/book-c7f3ce526c",
      "candidate_slug": "book-c7f3ce526c",
      "human_qa_required": true,
      "missing_required_files": [],
      "objective_audio_score": 8.8,
      "objective_audio_status": "PASS",
      "public_serving_status": "BLOCKED",
      "release_status": "HOLD_BENGALI_AUDIOBOOK_QA_REQUIRED",
      "rights_review_required": true,
      "sidecar_file_count": 3,
      "sync_usability_score": 7.6,
      "title": "খোকাবাবুর প্রত্যাবর্তন"
    },
    {
      "accessibility_qa_required": true,
      "audio_file_count": 1,
      "author": "রবীন্দ্রনাথ ঠাকুর",
      "automatic_improvement_count": 0,
      "candidate_dir": "internal/audiobook_lab/bengali_store_candidates/book-c85323409f",
      "candidate_slug": "book-c85323409f",
      "human_qa_required": true,
      "missing_required_files": [],
      "objective_audio_score": 8.8,
      "objective_audio_status": "PASS",
      "public_serving_status": "BLOCKED",
      "release_status": "HOLD_BENGALI_AUDIOBOOK_QA_REQUIRED",
      "rights_review_required": true,
      "sidecar_file_count": 3,
      "sync_usability_score": 7.6,
      "title": "জীবিত ও মৃত"
    },
    {
      "accessibility_qa_required": true,
      "audio_file_count": 1,
      "author": "রবীন্দ্রনাথ ঠাকুর",
      "automatic_improvement_count": 0,
      "candidate_dir": "internal/audiobook_lab/bengali_store_candidates/book-d19e96859f",
      "candidate_slug": "book-d19e96859f",
      "human_qa_required": true,
      "missing_required_files": [],
      "objective_audio_score": 8.8,
      "objective_audio_status": "PASS",
      "public_serving_status": "BLOCKED",
      "release_status": "HOLD_BENGALI_AUDIOBOOK_QA_REQUIRED",
      "rights_review_required": true,
      "sidecar_file_count": 3,
      "sync_usability_score": 7.6,
      "title": "গিন্নি"
    },
    {
      "accessibility_qa_required": true,
      "audio_file_count": 1,
      "author": "রবীন্দ্রনাথ ঠাকুর",
      "automatic_improvement_count": 0,
      "candidate_dir": "internal/audiobook_lab/bengali_store_candidates/book-d2fe532e1c",
      "candidate_slug": "book-d2fe532e1c",
      "human_qa_required": true,
      "missing_required_files": [],
      "objective_audio_score": 8.8,
      "objective_audio_status": "PASS",
      "public_serving_status": "BLOCKED",
      "release_status": "HOLD_BENGALI_AUDIOBOOK_QA_REQUIRED",
      "rights_review_required": true,
      "sidecar_file_count": 3,
      "sync_usability_score": 7.6,
      "title": "স্বর্ণমৃগ"
    },
    {
      "accessibility_qa_required": true,
      "audio_file_count": 1,
      "author": "রবীন্দ্রনাথ ঠাকুর",
      "automatic_improvement_count": 0,
      "candidate_dir": "internal/audiobook_lab/bengali_store_candidates/book-edfcf810c5",
      "candidate_slug": "book-edfcf810c5",
      "human_qa_required": true,
      "missing_required_files": [],
      "objective_audio_score": 8.8,
      "objective_audio_status": "PASS",
      "public_serving_status": "BLOCKED",
      "release_status": "HOLD_BENGALI_AUDIOBOOK_QA_REQUIRED",
      "rights_review_required": true,
      "sidecar_file_count": 3,
      "sync_usability_score": 8.0,
      "title": "ক্ষুধিত পাষাণ"
    },
    {
      "accessibility_qa_required": true,
      "audio_file_count": 1,
      "author": "রবীন্দ্রনাথ ঠাকুর",
      "automatic_improvement_count": 0,
      "candidate_dir": "internal/audiobook_lab/bengali_store_candidates/book-ef193ffc52",
      "candidate_slug": "book-ef193ffc52",
      "human_qa_required": true,
      "missing_required_files": [],
      "objective_audio_score": 8.8,
      "objective_audio_status": "PASS",
      "public_serving_status": "BLOCKED",
      "release_status": "HOLD_BENGALI_AUDIOBOOK_QA_REQUIRED",
      "rights_review_required": true,
      "sidecar_file_count": 3,
      "sync_usability_score": 8.0,
      "title": "দিদি"
    },
    {
      "accessibility_qa_required": true,
      "audio_file_count": 1,
      "author": "রবীন্দ্রনাথ ঠাকুর",
      "automatic_improvement_count": 0,
      "candidate_dir": "internal/audiobook_lab/bengali_store_candidates/book-f5d593e1f4",
      "candidate_slug": "book-f5d593e1f4",
      "human_qa_required": true,
      "missing_required_files": [],
      "objective_audio_score": 8.8,
      "objective_audio_status": "PASS",
      "public_serving_status": "BLOCKED",
      "release_status": "HOLD_BENGALI_AUDIOBOOK_QA_REQUIRED",
      "rights_review_required": true,
      "sidecar_file_count": 3,
      "sync_usability_score": 7.6,
      "title": "রামকানাইয়ের নির্বুদ্ধিতা"
    },
    {
      "accessibility_qa_required": true,
      "audio_file_count": 1,
      "author": "রবীন্দ্রনাথ ঠাকুর",
      "automatic_improvement_count": 0,
      "candidate_dir": "internal/audiobook_lab/bengali_store_candidates/book-fbdf2991ab",
      "candidate_slug": "book-fbdf2991ab",
      "human_qa_required": true,
      "missing_required_files": [],
      "objective_audio_score": 8.8,
      "objective_audio_status": "PASS",
      "public_serving_status": "BLOCKED",
      "release_status": "HOLD_BENGALI_AUDIOBOOK_QA_REQUIRED",
      "rights_review_required": true,
      "sidecar_file_count": 3,
      "sync_usability_score": 5.2,
      "title": "সুভা"
    },
    {
      "accessibility_qa_required": true,
      "audio_file_count": 1,
      "author": "বঙ্কিমচন্দ্র চট্টোপাধ্যায়",
      "automatic_improvement_count": 0,
      "candidate_dir": "internal/audiobook_lab/bengali_store_candidates/lokrahasya",
      "candidate_slug": "lokrahasya",
      "human_qa_required": true,
      "missing_required_files": [],
      "objective_audio_score": 8.8,
      "objective_audio_status": "PASS",
      "public_serving_status": "BLOCKED",
      "release_status": "HOLD_BENGALI_AUDIOBOOK_QA_REQUIRED",
      "rights_review_required": true,
      "sidecar_file_count": 3,
      "sync_usability_score": 4.0,
      "title": "লোকরহস্য"
    },
    {
      "accessibility_qa_required": true,
      "audio_file_count": 1,
      "author": "বঙ্কিমচন্দ্র চট্টোপাধ্যায়",
      "automatic_improvement_count": 0,
      "candidate_dir": "internal/audiobook_lab/bengali_store_candidates/mrinalini",
      "candidate_slug": "mrinalini",
      "human_qa_required": true,
      "missing_required_files": [],
      "objective_audio_score": 8.8,
      "objective_audio_status": "PASS",
      "public_serving_status": "BLOCKED",
      "release_status": "HOLD_BENGALI_AUDIOBOOK_QA_REQUIRED",
      "rights_review_required": true,
      "sidecar_file_count": 3,
      "sync_usability_score": 4.0,
      "title": "মৃণালিনী"
    },
    {
      "accessibility_qa_required": true,
      "audio_file_count": 1,
      "author": "বঙ্কিমচন্দ্র চট্টোপাধ্যায়",
      "automatic_improvement_count": 0,
      "candidate_dir": "internal/audiobook_lab/bengali_store_candidates/muchiram-gurer-jibanchorit",
      "candidate_slug": "muchiram-gurer-jibanchorit",
      "human_qa_required": true,
      "missing_required_files": [],
      "objective_audio_score": 8.8,
      "objective_audio_status": "PASS",
      "public_serving_status": "BLOCKED",
      "release_status": "HOLD_BENGALI_AUDIOBOOK_QA_REQUIRED",
      "rights_review_required": true,
      "sidecar_file_count": 3,
      "sync_usability_score": 8.0,
      "title": "মুচিরাম গুড়ের জীবনচরিত"
    },
    {
      "accessibility_qa_required": true,
      "audio_file_count": 1,
      "author": "শরৎচন্দ্র চট্টোপাধ্যায়",
      "automatic_improvement_count": 0,
      "candidate_dir": "internal/audiobook_lab/bengali_store_candidates/nishkriti",
      "candidate_slug": "nishkriti",
      "human_qa_required": true,
      "missing_required_files": [],
      "objective_audio_score": 8.8,
      "objective_audio_status": "PASS",
      "public_serving_status": "BLOCKED",
      "release_status": "HOLD_BENGALI_AUDIOBOOK_QA_REQUIRED",
      "rights_review_required": true,
      "sidecar_file_count": 3,
      "sync_usability_score": 4.0,
      "title": "নিষ্কৃতি"
    },
    {
      "accessibility_qa_required": true,
      "audio_file_count": 1,
      "author": "বঙ্কিমচন্দ্র চট্টোপাধ্যায়",
      "automatic_improvement_count": 0,
      "candidate_dir": "internal/audiobook_lab/bengali_store_candidates/radharani",
      "candidate_slug": "radharani",
      "human_qa_required": true,
      "missing_required_files": [],
      "objective_audio_score": 8.8,
      "objective_audio_status": "PASS",
      "public_serving_status": "BLOCKED",
      "release_status": "HOLD_BENGALI_AUDIOBOOK_QA_REQUIRED",
      "rights_review_required": true,
      "sidecar_file_count": 3,
      "sync_usability_score": 4.0,
      "title": "রাধারাণী"
    },
    {
      "accessibility_qa_required": true,
      "audio_file_count": 1,
      "author": "বঙ্কিমচন্দ্র চট্টোপাধ্যায়",
      "automatic_improvement_count": 0,
      "candidate_dir": "internal/audiobook_lab/bengali_store_candidates/yugalanguriya",
      "candidate_slug": "yugalanguriya",
      "human_qa_required": true,
      "missing_required_files": [],
      "objective_audio_score": 8.8,
      "objective_audio_status": "PASS",
      "public_serving_status": "BLOCKED",
      "release_status": "HOLD_BENGALI_AUDIOBOOK_QA_REQUIRED",
      "rights_review_required": true,
      "sidecar_file_count": 3,
      "sync_usability_score": 4.0,
      "title": "যুগলাঙ্গুরীয়"
    }
  ],
  "frontend_build_audio_files": [],
  "frontend_public_audio_files": [],
  "generated_at": "2026-07-02T10:37:31+00:00",
  "generated_by": "scripts/ingest_bengali_audiobook_store_candidates.py",
  "human_qa_required": true,
  "mode": "review",
  "output_dir": "internal/audiobook_lab/bengali_store_candidates",
  "public_audio_files": [],
  "public_audio_release": "PUBLIC_AUDIO_RELEASE_BLOCKED",
  "release_status": "HOLD_BENGALI_AUDIOBOOK_QA_REQUIRED",
  "rights_legal_owner_approval_required": true,
  "source_input_dir": "output/bengali_audiobook_polish/bengali-polish-queue-v1/bundles/ben"
}
