{
  "generated_at": "2026-06-20T20:30:24Z",
  "run_dir": "output/release-canary/2026-06-20-20-29-20",
  "overall_status": "PASS",
  "failed_command": "",
  "route_canary_status": "PASS",
  "backend_catalog_truth_status": "PASS",
  "dracula_live_status": "PASS",
  "payment_smoke_status": "PASS",
  "seo_status": "PASS",
  "social_preview_prod_status": "PASS",
  "audio_status": "PASS",
  "catalog_truth_status": "PASS",
  "daily_growth_audit_status": "PASS",
  "observability_status": "PASS",
  "regression_status": "PASS",
  "frontend_build_status": "PASS",
  "ux_go_no_go_status": "PASS",
  "owner_recommendation": "KEEP_DRACULA_LIVE",
  "public_mutation_performed": false,
  "paid_provider_calls_performed": false,
  "audiobook_enabled": false,
  "emails_or_social_posts_sent": false,
  "commands": [
    {
      "key": "route_canary",
      "label": "Route canary",
      "command": "npm run launch:post-deploy-route-canary",
      "critical": true,
      "status": "PASS",
      "returncode": 0,
      "duration_seconds": 2.837,
      "log_file": "output/release-canary/2026-06-20-20-29-20/01-route_canary.log",
      "warning_detected": false
    },
    {
      "key": "backend_catalog_truth",
      "label": "Backend catalog truth",
      "command": "npm run launch:backend-catalog-truth-canary",
      "critical": true,
      "status": "PASS",
      "returncode": 0,
      "duration_seconds": 10.172,
      "log_file": "output/release-canary/2026-06-20-20-29-20/02-backend_catalog_truth.log",
      "warning_detected": false
    },
    {
      "key": "production_parity",
      "label": "Production parity",
      "command": "npm run launch:production-parity",
      "critical": true,
      "status": "PASS",
      "returncode": 0,
      "duration_seconds": 2.118,
      "log_file": "output/release-canary/2026-06-20-20-29-20/03-production_parity.log",
      "warning_detected": false
    },
    {
      "key": "controlled_publication",
      "label": "Controlled publication precheck",
      "command": "npm run controlled-publication:precheck",
      "critical": true,
      "status": "PASS",
      "returncode": 0,
      "duration_seconds": 0.109,
      "log_file": "output/release-canary/2026-06-20-20-29-20/04-controlled_publication.log",
      "warning_detected": false
    },
    {
      "key": "payment_smoke",
      "label": "Payment smoke",
      "command": "npm run launch:payment-smoke",
      "critical": true,
      "status": "PASS",
      "returncode": 0,
      "duration_seconds": 0.124,
      "log_file": "output/release-canary/2026-06-20-20-29-20/05-payment_smoke.log",
      "warning_detected": false
    },
    {
      "key": "seo",
      "label": "SEO audit",
      "command": "npm run launch:seo-audit",
      "critical": false,
      "status": "PASS",
      "returncode": 0,
      "duration_seconds": 0.12,
      "log_file": "output/release-canary/2026-06-20-20-29-20/06-seo.log",
      "warning_detected": false
    },
    {
      "key": "social_preview_prod",
      "label": "Production social preview",
      "command": "npm run launch:social-preview-audit:prod",
      "critical": false,
      "status": "PASS",
      "returncode": 0,
      "duration_seconds": 0.901,
      "log_file": "output/release-canary/2026-06-20-20-29-20/07-social_preview_prod.log",
      "warning_detected": false
    },
    {
      "key": "audio",
      "label": "Audio audit",
      "command": "npm run launch:audio-audit",
      "critical": false,
      "status": "PASS",
      "returncode": 0,
      "duration_seconds": 0.155,
      "log_file": "output/release-canary/2026-06-20-20-29-20/08-audio.log",
      "warning_detected": false
    },
    {
      "key": "catalog_truth",
      "label": "Owner catalog truth audit",
      "command": "npm run owner:catalog-truth-audit",
      "critical": false,
      "status": "PASS",
      "returncode": 0,
      "duration_seconds": 0.112,
      "log_file": "output/release-canary/2026-06-20-20-29-20/09-catalog_truth.log",
      "warning_detected": false
    },
    {
      "key": "daily_growth_audit",
      "label": "Owner daily growth audit",
      "command": "npm run owner:daily-growth-audit",
      "critical": false,
      "status": "PASS",
      "returncode": 0,
      "duration_seconds": 0.103,
      "log_file": "output/release-canary/2026-06-20-20-29-20/10-daily_growth_audit.log",
      "warning_detected": false
    },
    {
      "key": "observability",
      "label": "Observability audit",
      "command": "npm run observability:audit",
      "critical": false,
      "status": "PASS",
      "returncode": 0,
      "duration_seconds": 0.1,
      "log_file": "output/release-canary/2026-06-20-20-29-20/11-observability.log",
      "warning_detected": false
    },
    {
      "key": "regression",
      "label": "Focused regression",
      "command": "npm run regression -- modules/13-public-content-governance.test.js modules/14-ux-conversion-static.test.js",
      "critical": true,
      "status": "PASS",
      "returncode": 0,
      "duration_seconds": 0.537,
      "log_file": "output/release-canary/2026-06-20-20-29-20/12-regression.log",
      "warning_detected": false
    },
    {
      "key": "frontend_build",
      "label": "Frontend build",
      "command": "npm --prefix frontend run build",
      "critical": true,
      "status": "PASS",
      "returncode": 0,
      "duration_seconds": 4.23,
      "log_file": "output/release-canary/2026-06-20-20-29-20/13-frontend_build.log",
      "warning_detected": true
    },
    {
      "key": "ux_go_no_go",
      "label": "Real-user UX go/no-go",
      "command": "npm run release:ux-go-no-go",
      "critical": false,
      "status": "PASS",
      "returncode": 0,
      "duration_seconds": 42.492,
      "log_file": "output/release-canary/2026-06-20-20-29-20/14-ux_go_no_go.log",
      "warning_detected": false
    }
  ]
}
