{
  "slug": "book-c7f3ce526c",
  "source_url": "https://bn.wikisource.org/wiki/গল্পগুচ্ছ_(প্রথম_খণ্ড)/খোকাবাবুর_প্রত্যাবর্তন",
  "source_name": "Bengali Wikisource",
  "source_license": "Underlying Bengali literary text is public domain in India and the U.S.; Wikisource transcription/source layer is reused under CC BY-SA terms.",
  "source_hash": "e6482b11503e888e9e9a2e5233cce17d2476164d8894433b520ecad24db04a05",
  "content_hash": "30747ea77e55c1a8b6227802d6e89078e79b2c348970d55960080001e376a954",
  "provenance_hash": "3c9cd2a93fd45bf28d8a5aac81a3d21ed4edfb221f354fa21f0716a9487d76d8",
  "rights_basis": "Author died in 1941, so the original literary work is public domain in India under life plus 60 years. Original publication before 1931 supports U.S. public-domain status.",
  "downloaded_at": "2026-05-20T09:08:20.763308+00:00",
  "source_format": "text/plain",
  "reader_facing_boilerplate_removed": true
}
